Workbook

Sheet Table-View
A1: 1. View Name | B1: Open_Tax_Lot_Non_Brokerage_Fact_V | F1: Please read review comments on Table Functional Description, Data Type and Business Definition
A2: 2. Table Name (From DA Team) - | B2: OPN_TAX_LOTS_NON_BKR_FACT
A3: 3. View Schema Name - SSDS_DAL_OWNER
A4: 4. Table Schema Name - TAXLOT_OWNER
A5: 5. Table Functional Description /Comment in Oracle/Redshift - | B5: This table contains records for taxlots non brokerage which are Open and whose impact is yet to considered as realized gain/loss. | F5: BA Responsbility | G5: BA Responsbility | H5: BA Responsbility | I5: DA Responsibility
A6: 6. Filter Criteria - Please see ETL Notes sheet.
A7: 7. Grain - Please see Grain Columns sheet.
A8: Lighthouse Target | N8: Source | X8: Transformation
A9: Logical Name of Attribute (Name of column in View without underscores) | B9: DA Comments to BA | C9: Physical Name of Attribute (Name of column in Table) Supplied by DA Team | D9: Data type in Oracle VARCHAR2(n), DATE, NUMBER(m,n), TIMETSTAMP(6) | E9: Nullable in Table and in Oracle View NULL, NOT NULL | F9: Data type in Redshift | G9: Nullable in View in Redshift | H9: Business Definition (To go into comments and into Meta Data Hub) | I9: Sample data values | J9: Action on Attribute Add,Update,Remove, Blank | K9: Comments on when it was added / updated. List the PBI or Bug number. | L9: Include in View. Populated with N only when not to be shown in the view. | M9: Is on Data Model DA responsibility | N9: Model Data Type match TRUE/FALSE DA Responsibilty | O9: model defs. Match | R9: Is On table | S9: On View | T9: Source Schema | U9: Source Table | V9: Source Attribute Name | W9: Data Type | X9: Nullable? | Y9: Transformation /Business Rules /Join Conditions | Z9: Notes / Comments
A10: Open Tax Lots Non Brokerage Fact Id | D10: NUMBER(38,0) | E10: No | F10: NUMERIC(38,0) | G10: No | H10: This is Surrogate Key for this table. Used as Primary Key as wel | M10: =VLOOKUP(A10,Model!C$2:J$93,2,FALSE)=C10 -> #N/A | O10: =VLOOKUP(A10,Model!C$2:J$93,3,FALSE)=H10 -> #N/A | P10: =VLOOKUP(A10,Model!C$2:J$93,3,FALSE) -> #N/A | Q10: =VLOOKUP(A10,Model!C$2:J$93,8,FALSE) -> #N/A | R10: =VLOOKUP(C10,Table!A$2:F$98,1,FALSE)=C10 -> #N/A | S10: =VLOOKUP(SUBSTITUTE(A10," ","_"),View!A$2:I$106,1,FALSE) -> #N/A | W10: NUMBER(38,0) | X10: No
A11: Source System Code | C11: SRC_STM_CD | D11: VARCHAR2(40) | E11: Yes | F11: Character Varying(40) | G11: Yes | H11: TAX_LOT_OPN_MSTR.SRC_STM_ID | M11: =VLOOKUP(A11,Model!C$2:J$93,2,FALSE)=C11 -> TRUE | O11: =VLOOKUP(A11,Model!C$2:J$93,3,FALSE)=H11 -> FALSE | P11: =VLOOKUP(A11,Model!C$2:J$93,3,FALSE) -> MAXIT: Hardcode ??? We need to setup a source system RJT Source: TAX_LOT_OPN_MSTR.SRC_STM_ID | Q11: =VLOOKUP(A11,Model!C$2:J$93,8,FALSE) -> 2 | R11: =VLOOKUP(C11,Table!A$2:F$98,1,FALSE)=C11 -> TRUE | S11: =VLOOKUP(SUBSTITUTE(A11," ","_"),View!A$2:I$106,1,FALSE) -> SOURCE_SYSTEM_CODE | T11: COMMON_OWNER | U11: SRC_STM_DIM | V11: SRC_STM_CD | W11: VARCHAR2(40) | X11: Yes | Y11: Use SRC_STM_ID to get code
A12: Arrangement Id | C12: AR_ID | D12: NUMBER(38,0) | E12: Yes | F12: NUMBER(38,0) | G12: Yes | H12: Arrangement Id for the account Source:TAX_LOT_OPN_MSTR.AR_ID | M12: =VLOOKUP(A12,Model!C$2:J$93,2,FALSE)=C12 -> TRUE | O12: =VLOOKUP(A12,Model!C$2:J$93,3,FALSE)=H12 -> FALSE | P12: =VLOOKUP(A12,Model!C$2:J$93,3,FALSE) -> Arrangement Id for the account MAXIT Source:TAX_LOT_DTL_OPN/CLS.AR_ID RJT Source:TAX_LOT_OPN_MSTR.AR_ID | Q12: =VLOOKUP(A12,Model!C$2:J$93,8,FALSE) -> 3 | R12: =VLOOKUP(C12,Table!A$2:F$98,1,FALSE)=C12 -> TRUE | S12: =VLOOKUP(SUBSTITUTE(A12," ","_"),View!A$2:I$106,1,FALSE) -> ARRANGEMENT_ID | T12: TAXLOT_STG_OWNER | U12: OPN_TAX_LOTS_NONBKR_TGT | V12: AR_ID | W12: NUMBER | X12: Yes
A13: CIRD Product Id | C13: CIRD_PD_ID | D13: NUMBER(38,0) | E13: Yes | F13: NUMBER(38,0) | G13: Yes | H13: RJT Source: TAX_LOT_OPN_MSTR.CCAL_PD_ID Lookup on IMT_PD_DIM using CCAL_PD_ID PD_ID from CIRD - can be used as join key if date context is supplied at query time | M13: =VLOOKUP(A13,Model!C$2:J$93,2,FALSE)=C13 -> TRUE | O13: =VLOOKUP(A13,Model!C$2:J$93,3,FALSE)=H13 -> FALSE | P13: =VLOOKUP(A13,Model!C$2:J$93,3,FALSE) -> MAXIT Source: TAX_LOT_DTL_OPN/CLS.PD_ID RJT Source: TAX_LOT_OPN_MSTR.CCAL_PD_ID Lookup on IMT_PD_DIM using CL_PD_ID PD_ID from CIRD - can be used as join key if date context is supplied at query time | Q13: =VLOOKUP(A13,Model!C$2:J$93,8,FALSE) -> 4 | R13: =VLOOKUP(C13,Table!A$2:F$98,1,FALSE)=C13 -> TRUE | S13: =VLOOKUP(SUBSTITUTE(A13," ","_"),View!A$2:I$106,1,FALSE) -> CIRD_PRODUCT_ID | T13: CCAL_REPL_OWNER | U13: CCAL_CIRD_PD_MAP | V13: CIRD_PD_ID | W13: NUMBER | X13: Yes | Y13: Look up on CCAL_CIRD_PD_MAP where CCAL_PD_ID = TAX_LOT_OPN_MSTR.CCAL_PD_ID, pick- CIRD_PD_ID AND ACTV_F = 'Y'
A14: CCAL Product Id | C14: CCAL_PD_ID | D14: NUMBER(38,0) | E14: Yes | F14: NUMBER(38,0) | G14: Yes | H14: Product Id assigned by CCAL RJT Source: TAX_LOT_OPN_MSTR.CCAL_PD_ID | M14: =VLOOKUP(A14,Model!C$2:J$93,2,FALSE)=C14 -> TRUE | O14: =VLOOKUP(A14,Model!C$2:J$93,3,FALSE)=H14 -> FALSE | P14: =VLOOKUP(A14,Model!C$2:J$93,3,FALSE) -> Product Id assigned by CCAL MAXIT Source: TAX_LOT_DTL_OPN/CLS.PD_ID RJT Source: TAX_LOT_OPN_MSTR.CCAL_PD_ID | Q14: =VLOOKUP(A14,Model!C$2:J$93,8,FALSE) -> 5 | R14: =VLOOKUP(C14,Table!A$2:F$98,1,FALSE)=C14 -> TRUE | S14: =VLOOKUP(SUBSTITUTE(A14," ","_"),View!A$2:I$106,1,FALSE) -> CCAL_PRODUCT_ID | T14: TAXLOT_STG_OWNER | U14: OPN_TAX_LOTS_NONBKR_TGT | V14: CCAL_PD_ID | W14: NUMBER | X14: Yes
A15: Accounting Type Code | C15: ACG_TP_CD | D15: VARCHAR2(1) | E15: Yes | F15: Character Varying(1) | G15: Yes | H15: RJT Source: TAX_LOT_OPN_MSTR.ACG_TP_CODE Accounting type code P=Principal I=Income | M15: =VLOOKUP(A15,Model!C$2:J$93,2,FALSE)=C15 -> TRUE | O15: =VLOOKUP(A15,Model!C$2:J$93,3,FALSE)=H15 -> FALSE | P15: =VLOOKUP(A15,Model!C$2:J$93,3,FALSE) -> MAXIT Source: TAXLOT_DTL_OPN.AC_TP RJT Source: TAX_LOT_OPN_MSTR.ACG_TP_CODE Accounting type code from SIS (e.g., 1,2,6). 1= Cash Account 2= Margin Account 3= Special lot 2019 5= Special lot 2013 6= Short margin Account | Q15: =VLOOKUP(A15,Model!C$2:J$93,8,FALSE) -> 8 | R15: =VLOOKUP(C15,Table!A$2:F$98,1,FALSE)=C15 -> TRUE | S15: =VLOOKUP(SUBSTITUTE(A15," ","_"),View!A$2:I$106,1,FALSE) -> ACCOUNTING_TYPE_CODE | T15: TAXLOT_STG_OWNER | U15: OPN_TAX_LOTS_NONBKR_TGT | V15: AC_TP_CODE | W15: VARCHAR2(1) | X15: Yes
A16: Tax Lot External Reference Key Primary | C16: TAX_LOT_EXT_REFR_KEY_PRIM | D16: VARCHAR2(50) | E16: Yes | F16: Character Varying(50) | G16: Yes | H16: Taxlot sequence unique identifier assgined when a lot is generated in the source system. | M16: =VLOOKUP(A16,Model!C$2:J$93,2,FALSE)=C16 -> TRUE | O16: =VLOOKUP(A16,Model!C$2:J$93,3,FALSE)=H16 -> FALSE | P16: =VLOOKUP(A16,Model!C$2:J$93,3,FALSE) -> MAXIT source: MAXIT_IFCE_SEQ_ID RJT Source: TAX_LOT_OPN_MSTR.TAX_LOT_EXT_REFR_KEY_PRIM | Q16: =VLOOKUP(A16,Model!C$2:J$93,8,FALSE) -> 9 | R16: =VLOOKUP(C16,Table!A$2:F$98,1,FALSE)=C16 -> TRUE | S16: =VLOOKUP(SUBSTITUTE(A16," ","_"),View!A$2:I$106,1,FALSE) -> TAX_LOT_EXTERNAL_REFERENCE_KEY_PRIMARY | T16: TAXLOT_STG_OWNER | U16: OPN_TAX_LOTS_NONBKR_TGT | V16: TAX_LOT_EXT_REFR_KEY_PRIM | W16: VARCHAR2(50) | X16: Yes
A17: Tax Lot External Reference Key Secondary | C17: TAX_LOT_EXT_REFR_KEY_SCDY | D17: VARCHAR2(40) | E17: Yes | F17: Character Varying(40) | G17: Yes | H17: Secondary Sequence identifier of the debited tax lo assigned in the source system. Its optional not always populated | M17: =VLOOKUP(A17,Model!C$2:J$93,2,FALSE)=C17 -> TRUE | O17: =VLOOKUP(A17,Model!C$2:J$93,3,FALSE)=H17 -> FALSE | P17: =VLOOKUP(A17,Model!C$2:J$93,3,FALSE) -> source:TAXLOT_DTL_OPN.MAXIT_REL_IFCE_SEQ_ID RJT Source: TAX_LOT_OPN_MSTR.TAX_LOT_EXT_REFR_KEY_SCDY | Q17: =VLOOKUP(A17,Model!C$2:J$93,8,FALSE) -> 10 | R17: =VLOOKUP(C17,Table!A$2:F$98,1,FALSE)=C17 -> TRUE | S17: =VLOOKUP(SUBSTITUTE(A17," ","_"),View!A$2:I$106,1,FALSE) -> TAX_LOT_EXTERNAL_REFERENCE_KEY_SECONDARY | T17: TAXLOT_STG_OWNER | U17: OPN_TAX_LOTS_NONBKR_TGT | V17: TAX_LOT_EXT_REFR_KEY_SCDY | W17: VARCHAR2(40) | X17: Yes
A18: Tax Lot External Reference Key Tertiary | C18: TAX_LOT_EXT_REFR_KEY_TRTY | D18: NUMBER(38,0) | E18: Yes | F18: NUMERIC(38,0) | G18: Yes | H18: Sequence number identifier of transaction debited with a DLVR or Sell. Its optional not always popualted. | M18: =VLOOKUP(A18,Model!C$2:J$93,2,FALSE)=C18 -> TRUE | O18: =VLOOKUP(A18,Model!C$2:J$93,3,FALSE)=H18 -> FALSE | P18: =VLOOKUP(A18,Model!C$2:J$93,3,FALSE) -> Source: TAXLOT_DTL_OPN.MAXIT_TXN_LOT_ID RJT Source: TAX_LOT_OPN_MSTR.TAX_LOT_EXT_REFR_KEY_TRTY | Q18: =VLOOKUP(A18,Model!C$2:J$93,8,FALSE) -> 11 | R18: =VLOOKUP(C18,Table!A$2:F$98,1,FALSE)=C18 -> TRUE | S18: =VLOOKUP(SUBSTITUTE(A18," ","_"),View!A$2:I$106,1,FALSE) -> TAX_LOT_EXTERNAL_REFERENCE_KEY_TERTIARY | T18: TAXLOT_STG_OWNER | U18: OPN_TAX_LOTS_NONBKR_TGT | V18: TAX_LOT_EXT_REFR_KEY_TRTY | W18: NUMBER(38,0) | X18: Yes
A19: Tax Lot External Reference Key Quaternary | C19: TAX_LOT_EXT_REFR_KEY_QTRNY | D19: NUMBER(38,0) | E19: Yes | F19: NUMERIC(38,0) | G19: Yes | H19: Unique system generated identifier used to identify taxlots and create associations between taxlots. | M19: =VLOOKUP(A19,Model!C$2:J$93,2,FALSE)=C19 -> TRUE | O19: =VLOOKUP(A19,Model!C$2:J$93,3,FALSE)=H19 -> FALSE | P19: =VLOOKUP(A19,Model!C$2:J$93,3,FALSE) -> SOurce: TAXLOT_DTL_OPN.REL_LOT_ID RJT Source: TAX_LOT_OPN_MSTR.TAX_LOT_EXT_REFR_KEY_QTRNY | Q19: =VLOOKUP(A19,Model!C$2:J$93,8,FALSE) -> 12 | R19: =VLOOKUP(C19,Table!A$2:F$98,1,FALSE)=C19 -> TRUE | S19: =VLOOKUP(SUBSTITUTE(A19," ","_"),View!A$2:I$106,1,FALSE) -> TAX_LOT_EXTERNAL_REFERENCE_KEY_QUATERNARY | T19: TAXLOT_STG_OWNER | U19: OPN_TAX_LOTS_NONBKR_TGT | V19: TAX_LOT_EXT_REFR_KEY_QTRNY | W19: NUMBER(38,0) | X19: Yes
A20: End Date | C20: END_DT | D20: DATE | E20: No | F20: Timestamp without time zone | G20: No | H20: Date on which row is no longer active. Specify as MyDate >= EFF_DT AND MyDate < END_DT to select a row that is active@MyDate | M20: =VLOOKUP(A20,Model!C$2:J$93,2,FALSE)=C20 -> TRUE | O20: =VLOOKUP(A20,Model!C$2:J$93,3,FALSE)=H20 -> FALSE | P20: =VLOOKUP(A20,Model!C$2:J$93,3,FALSE) -> MAXIT Source: TAXLOT_DTL_OPN.END_DT RJT Source: TAX_LOT_OPN_ASOF.EFF_TO_DT | Q20: =VLOOKUP(A20,Model!C$2:J$93,8,FALSE) -> 13 | R20: =VLOOKUP(C20,Table!A$2:F$98,1,FALSE)=C20 -> TRUE | S20: =VLOOKUP(SUBSTITUTE(A20," ","_"),View!A$2:I$106,1,FALSE) -> END_DATE | T20: TAXLOT_STG_OWNER | U20: OPN_TAX_LOTS_NONBKR_TGT | V20: EFF_TO_DT | W20: DATE | X20: No
A21: Effective Date | C21: EFF_DT | D21: DATE | E21: Yes | F21: Timestamp without time zone | G21: Yes | H21: Specify as MyDate >= EFF_DT AND MyDate < END_DT to select a row that is active@MyDate | M21: =VLOOKUP(A21,Model!C$2:J$93,2,FALSE)=C21 -> TRUE | O21: =VLOOKUP(A21,Model!C$2:J$93,3,FALSE)=H21 -> FALSE | P21: =VLOOKUP(A21,Model!C$2:J$93,3,FALSE) -> MAXIT Source: TAXLOT_DTL_OPN.EFF_DT_x000D_ RJT Source: TAX_LOT_OPN_ASOF.EFF_FM_DT_x000D_ _x000D_ | Q21: =VLOOKUP(A21,Model!C$2:J$93,8,FALSE) -> 14 | R21: =VLOOKUP(C21,Table!A$2:F$98,1,FALSE)=C21 -> TRUE | S21: =VLOOKUP(SUBSTITUTE(A21," ","_"),View!A$2:I$106,1,FALSE) -> EFFECTIVE_DATE | T21: TAXLOT_STG_OWNER | U21: OPN_TAX_LOTS_NONBKR_TGT | V21: EFF_FM_DT | W21: DATE | X21: Yes
A22: Accounting Type Name | C22: ACG_TP_NM | D22: VARCHAR2(500) | E22: Yes | F22: Character Varying(500) | G22: Yes | H22: TAX_LOT_OPN_MSTR.ACG_TP_CODE Lookup on Accounting Type Dimension Accounting type name (e.g., cash account,margin account) | M22: =VLOOKUP(A22,Model!C$2:J$93,2,FALSE)=C22 -> TRUE | O22: =VLOOKUP(A22,Model!C$2:J$93,3,FALSE)=H22 -> FALSE | P22: =VLOOKUP(A22,Model!C$2:J$93,3,FALSE) -> MAXIT Source: TAXLOT_DTL_OPN.AC_TP RJT Source: TAX_LOT_OPN_MSTR.ACG_TP_CODE Lookup on Accounting Type Dimension Accounting type name (e.g., cash account,margin account) | Q22: =VLOOKUP(A22,Model!C$2:J$93,8,FALSE) -> 16 | R22: =VLOOKUP(C22,Table!A$2:F$98,1,FALSE)=C22 -> TRUE | S22: =VLOOKUP(SUBSTITUTE(A22," ","_"),View!A$2:I$106,1,FALSE) -> ACCOUNTING_TYPE_NAME | T22: COMMON_OWNER | U22: ACG_TP_DIM | V22: ACG_TP_NM | W22: VARCHAR2(500) | X22: Yes | Y22: Lookup on Accounting Type Dimension Use TAX_LOT_OPN_MSTR.ACG_TP_CODE to get ACG_TP_NM
A23: Acquired Date | C23: ACQ_DT | D23: DATE | E23: Yes | F23: Timestamp without time zone | G23: Yes | H23: Always the buy/opening lot opening date. When there is a sell, the buy date against which the sell happened will be populated. If there are multiple buys against a sell, the sell is broken down into multiple taxlots. Note: This is sometime referred to as opening trade date. | M23: =VLOOKUP(A23,Model!C$2:J$93,2,FALSE)=C23 -> TRUE | O23: =VLOOKUP(A23,Model!C$2:J$93,3,FALSE)=H23 -> FALSE | P23: =VLOOKUP(A23,Model!C$2:J$93,3,FALSE) -> Date on which the lot was acquired_x000D_ MAXIT source: TAXLOT_DTL_OPN.ACQ_DT_x000D_ RJT Source:TAX_LOT_OPN_MSTR.TD_x000D_ _x000D_ | Q23: =VLOOKUP(A23,Model!C$2:J$93,8,FALSE) -> 19 | R23: =VLOOKUP(C23,Table!A$2:F$98,1,FALSE)=C23 -> TRUE | S23: =VLOOKUP(SUBSTITUTE(A23," ","_"),View!A$2:I$106,1,FALSE) -> ACQUIRED_DATE | T23: TAXLOT_STG_OWNER | U23: OPN_TAX_LOTS_NONBKR_TGT | V23: ACQ_DT | W23: DATE | X23: Yes
A24: Adjusted Cost | C24: ADJ_COST | D24: NUMBER(22,6) | E24: Yes | F24: NUMERIC(22,6) | G24: Yes | H24: For a Buy, the tax cost is shown. For a Sell, Tax Cost sold is populated. | M24: =VLOOKUP(A24,Model!C$2:J$93,2,FALSE)=C24 -> TRUE | O24: =VLOOKUP(A24,Model!C$2:J$93,3,FALSE)=H24 -> FALSE | P24: =VLOOKUP(A24,Model!C$2:J$93,3,FALSE) -> Adjusted cost for the Lot MAXIT source: TAXLOT_DTL_OPN.ADJ_COST RJT Source: TAX_LOT_OPN_ASOF NML_CCY_ASOF_ADJ_COST_AMT | Q24: =VLOOKUP(A24,Model!C$2:J$93,8,FALSE) -> 20 | R24: =VLOOKUP(C24,Table!A$2:F$98,1,FALSE)=C24 -> TRUE | S24: =VLOOKUP(SUBSTITUTE(A24," ","_"),View!A$2:I$106,1,FALSE) -> ADJUSTED_COST | T24: TAXLOT_STG_OWNER | U24: OPN_TAX_LOTS_NONBKR_TGT | V24: SBC_ASOF_ADJ_COST_AMT | W24: NUMBER(22,6) | X24: Yes | Y24: ADJ_COST, case when (CCY_CODE ='USD' or (EXG_RATE is NULL OR EXG_RATE = 0)) THEN ADJ_COST ELSE ADJ_COST * EXG_RATE END SBC_ADJ_COST
A25: Currency Code | C25: CCY_CD | D25: VARCHAR2(7) | E25: Yes | F25: Character Varying(7) | G25: Yes | H25: ISO certified3 alpha codes. | M25: =VLOOKUP(A25,Model!C$2:J$93,2,FALSE)=C25 -> TRUE | O25: =VLOOKUP(A25,Model!C$2:J$93,3,FALSE)=H25 -> FALSE | P25: =VLOOKUP(A25,Model!C$2:J$93,3,FALSE) -> MAXIT Source: TAXLOT_DTL_OPN.CCY_CODE RJT Source: TAX_LOT_OPN_ASOF.NML_ISO_CCY_CODE | Q25: =VLOOKUP(A25,Model!C$2:J$93,8,FALSE) -> 23 | R25: =VLOOKUP(C25,Table!A$2:F$98,1,FALSE)=C25 -> TRUE | S25: =VLOOKUP(SUBSTITUTE(A25," ","_"),View!A$2:I$106,1,FALSE) -> CURRENCY_CODE | T25: TAXLOT_STG_OWNER | U25: OPN_TAX_LOTS_NONBKR_TGT | V25: STM_BASE_ISO_CCY_CODE | W25: VARCHAR2(7) | X25: Yes
A26: Certificate Number | C26: CTF_NUM | D26: VARCHAR2(40) | E26: Yes | F26: Character Varying(40) | G26: Yes | H26: Certificate Number Provided by CBRS. | M26: =VLOOKUP(A26,Model!C$2:J$93,2,FALSE)=C26 -> TRUE | O26: =VLOOKUP(A26,Model!C$2:J$93,3,FALSE)=H26 -> FALSE | P26: =VLOOKUP(A26,Model!C$2:J$93,3,FALSE) -> MAXIT Source:TAXLOT_DTL_OPN.CTF_NUM RJT Source: TAX_LOT_OPN_MSTR.TAX_LOT_CTF_NUM | Q26: =VLOOKUP(A26,Model!C$2:J$93,8,FALSE) -> 24 | R26: =VLOOKUP(C26,Table!A$2:F$98,1,FALSE)=C26 -> TRUE | S26: =VLOOKUP(SUBSTITUTE(A26," ","_"),View!A$2:I$106,1,FALSE) -> CERTIFICATE_NUMBER | T26: TAXLOT_STG_OWNER | U26: OPN_TAX_LOTS_NONBKR_TGT | V26: TAX_LOT_CTF_NUM | W26: VARCHAR2(40) | X26: Yes
A27: Certificate Number Prefix | C27: CTF_NUM_PFX | D27: VARCHAR2(40) | E27: Yes | F27: Character Varying(40) | G27: Yes | H27: Certificate Number Prefix Provided by CBRS. | M27: =VLOOKUP(A27,Model!C$2:J$93,2,FALSE)=C27 -> TRUE | O27: =VLOOKUP(A27,Model!C$2:J$93,3,FALSE)=H27 -> FALSE | P27: =VLOOKUP(A27,Model!C$2:J$93,3,FALSE) -> MAXIT Source:TAXLOT_DTL_OPN.CTF_NUM_PFX RJT Source: TAX_LOT_OPN_MSTR.TAX_LOT_CTF_NUM_PFX | Q27: =VLOOKUP(A27,Model!C$2:J$93,8,FALSE) -> 25 | R27: =VLOOKUP(C27,Table!A$2:F$98,1,FALSE)=C27 -> TRUE | S27: =VLOOKUP(SUBSTITUTE(A27," ","_"),View!A$2:I$106,1,FALSE) -> CERTIFICATE_NUMBER_PREFIX | T27: TAXLOT_STG_OWNER | U27: OPN_TAX_LOTS_NONBKR_TGT | V27: TAX_LOT_CTF_NUM_PFX | W27: VARCHAR2(40) | X27: Yes
A28: Cost Basis Legislation Coverage Code | C28: COST_BSS_LEGS_CVR_CD | D28: VARCHAR2(1) | E28: Yes | F28: Character Varying(1) | G28: Yes | H28: Cost Basis Legislation Coverage: “covered” securities are those impacted by the cost basis legislation (which is dependent on the security type and acquisition date) and subject to the new IRS reporting requirements. | M28: =VLOOKUP(A28,Model!C$2:J$93,2,FALSE)=C28 -> TRUE | O28: =VLOOKUP(A28,Model!C$2:J$93,3,FALSE)=H28 -> FALSE | P28: =VLOOKUP(A28,Model!C$2:J$93,3,FALSE) -> Cost Basis Legislation Coverage: ?covered? securities are those impacted by the cost basis legislation (which is dependent on the security type and acquisition date) and subject to the new IRS reporting requirements. U = Uncovered Tax Lot C = Covered Tax Lot MAXIT Source: TAXLOT_DTL_OPN.CVRD_UNCVRD RJT Source: TAX_LOT_OPN_MSTR.CVRD_F | Q28: =VLOOKUP(A28,Model!C$2:J$93,8,FALSE) -> 26 | R28: =VLOOKUP(C28,Table!A$2:F$98,1,FALSE)=C28 -> TRUE | S28: =VLOOKUP(SUBSTITUTE(A28," ","_"),View!A$2:I$106,1,FALSE) -> COST_BASIS_LEGISLATION_COVERAGE_CODE | T28: TAXLOT_STG_OWNER | U28: OPN_TAX_LOTS_NONBKR_TGT | V28: CVRD_UNCVRD | W28: VARCHAR2(1) | X28: Yes
A29: Disallowed Wash Sale Amount | C29: DISALWD_WASH_SALE_AMT | D29: NUMBER(22,6) | E29: Yes | F29: NUMERIC(22,6) | G29: Yes | H29: A wash sale is sale of a security at a loss and repurchase of the same or substantially identical security shortly before or after. The wash-sale rule states that the tax loss will be disallowed if you buy the same security, a contract or option to buy the security, or a "substantially identical" security, within 30 days before or after the date you sold the loss-generating investment | M29: =VLOOKUP(A29,Model!C$2:J$93,2,FALSE)=C29 -> TRUE | O29: =VLOOKUP(A29,Model!C$2:J$93,3,FALSE)=H29 -> FALSE | P29: =VLOOKUP(A29,Model!C$2:J$93,3,FALSE) -> MAXIT Source: TAXLOT_DTL_OPN.DISALWD_WASHSALE_AMT RJT Source: TAX_LOT_OPN_MSTR.NML_CCY_WASH_SALE_AMT | Q29: =VLOOKUP(A29,Model!C$2:J$93,8,FALSE) -> 27 | R29: =VLOOKUP(C29,Table!A$2:F$98,1,FALSE)=C29 -> TRUE | S29: =VLOOKUP(SUBSTITUTE(A29," ","_"),View!A$2:I$106,1,FALSE) -> DISALLOWED_WASH_SALE_AMOUNT | T29: TAXLOT_STG_OWNER | U29: OPN_TAX_LOTS_NONBKR_TGT | V29: SBC_WASH_SALE_AMT | W29: NUMBER(22,6) | X29: Yes
A30: Exchange Rate | C30: EXG_RATE | D30: NUMBER(22,6) | E30: Yes | F30: NUMERIC(22,6) | G30: Yes | H30: This is an exchange rate for foreign currency. | M30: =VLOOKUP(A30,Model!C$2:J$93,2,FALSE)=C30 -> TRUE | O30: =VLOOKUP(A30,Model!C$2:J$93,3,FALSE)=H30 -> FALSE | P30: =VLOOKUP(A30,Model!C$2:J$93,3,FALSE) -> MAXIT Source: TAXLOT_DTL_OPN.EXG_RATE RJT Source: TAX_LOT_OPN_ASOF.SBC_EXG_RATE | Q30: =VLOOKUP(A30,Model!C$2:J$93,8,FALSE) -> 28 | R30: =VLOOKUP(C30,Table!A$2:F$98,1,FALSE)=C30 -> TRUE | S30: =VLOOKUP(SUBSTITUTE(A30," ","_"),View!A$2:I$106,1,FALSE) -> EXCHANGE_RATE | T30: TAXLOT_STG_OWNER | U30: OPN_TAX_LOTS_NONBKR_TGT | V30: SBC_EXG_RATE | W30: NUMBER(22,6) | X30: Yes
A31: Fair Market Value Of Gift Or Inheritance | C31: FAIR_MKT_VAL_OF_GIFT_OR_INHTN | D31: NUMBER(22,6) | E31: Yes | F31: NUMERIC(22,6) | G31: Yes | H31: Fair market value of the tax lot at the point of gifting or inheritance For gifted or inherited trns only. | M31: =VLOOKUP(A31,Model!C$2:J$93,2,FALSE)=C31 -> TRUE | O31: =VLOOKUP(A31,Model!C$2:J$93,3,FALSE)=H31 -> FALSE | P31: =VLOOKUP(A31,Model!C$2:J$93,3,FALSE) -> MAXIT Source: TAXLOT_DTL_OPN.FMV RJT SOurce: TAX_LOT_OPN_ASOF.NML_CCY_ASOF_FAIR_MKT_VAL_AMT For MAXIT (Brokerage) Fair market value of the tax lot at the point of gifting or inheritance Source: FMV For gifted or inherited transactions only. Sourced from: 1) account to account RAD Activity receive record sent to Maxit from RJ 2) CBRS record received from contra firm 3) manual entry by business | Q31: =VLOOKUP(A31,Model!C$2:J$93,8,FALSE) -> 29 | R31: =VLOOKUP(C31,Table!A$2:F$98,1,FALSE)=C31 -> TRUE | S31: =VLOOKUP(SUBSTITUTE(A31," ","_"),View!A$2:I$106,1,FALSE) -> FAIR_MARKET_VALUE_OF_GIFT_OR_INHERITANCE | T31: TAXLOT_STG_OWNER | U31: OPN_TAX_LOTS_NONBKR_TGT | V31: SBC_ASOF_FAIR_MKT_VAL_AMT | W31: NUMBER(22,6) | X31: Yes | Y31: FMV FAIR_MKT_VAL_OF_GIFT_OR_INHTN, case when (CCY_CODE ='USD' or (EXG_RATE is NULL OR EXG_RATE = 0)) THEN FMV ELSE FMV * EXG_RATE END SBC_FAIR_MKT_VAL
A32: Gift Date | C32: GIFT_DT | D32: DATE | E32: Yes | F32: Timestamp without time zone | G32: Yes | H32: Date of death for inheritance or Date of a gifted taxlot. | M32: =VLOOKUP(A32,Model!C$2:J$93,2,FALSE)=C32 -> TRUE | O32: =VLOOKUP(A32,Model!C$2:J$93,3,FALSE)=H32 -> FALSE | P32: =VLOOKUP(A32,Model!C$2:J$93,3,FALSE) -> MAXIT Source: TAXLOT_DTL_OPN.GIFT_DT RJT Source: TAX_LOT_OPN_MSTR.GIFT_DT For gifted tax lots this gives date of gift. Source: GIFT_DT | Q32: =VLOOKUP(A32,Model!C$2:J$93,8,FALSE) -> 30 | R32: =VLOOKUP(C32,Table!A$2:F$98,1,FALSE)=C32 -> TRUE | S32: =VLOOKUP(SUBSTITUTE(A32," ","_"),View!A$2:I$106,1,FALSE) -> GIFT_DATE | T32: TAXLOT_STG_OWNER | U32: OPN_TAX_LOTS_NONBKR_TGT | V32: GIFT_DT | W32: DATE | X32: Yes
A33: Position Inception Date | C33: POS_INCPTN_DT | D33: DATE | E33: Yes | F33: Timestamp without time zone | G33: Yes | H33: Holding date of the opening tax lot. Is available on the sell transaction as well. Note: This should coincide with the acquisition date unless the sale is affected by an action in which the acquisition date changes but the holding date stays the same. i.e. wash sale, gifts, etc.) | M33: =VLOOKUP(A33,Model!C$2:J$93,2,FALSE)=C33 -> TRUE | O33: =VLOOKUP(A33,Model!C$2:J$93,3,FALSE)=H33 -> FALSE | P33: =VLOOKUP(A33,Model!C$2:J$93,3,FALSE) -> Holding date of the opening tax lot. Is available on the sell transaction as well. Note: This should coincide with the acquisition date unless the sale is affected by an action in which the acquisition date changes but the holding date stays the same. i.e. wash sale, gifts, etc.) Used to calculate the term for most cases MAXIT Source: TAXLOT_DTL_OPN.HLDG_DT RJT Source: TAX_LOT_OPN_MSTR.POS_INCPTN_DT | Q33: =VLOOKUP(A33,Model!C$2:J$93,8,FALSE) -> 31 | R33: =VLOOKUP(C33,Table!A$2:F$98,1,FALSE)=C33 -> TRUE | S33: =VLOOKUP(SUBSTITUTE(A33," ","_"),View!A$2:I$106,1,FALSE) -> POSITION_INCEPTION_DATE | T33: TAXLOT_STG_OWNER | U33: OPN_TAX_LOTS_NONBKR_TGT | V33: POS_INCPTN_DT | W33: DATE | X33: Yes
A34: Long Short Position Code | C34: LONG_SHRT_POS_CD | D34: VARCHAR2(1) | E34: Yes | F34: Character Varying(1) | G34: Yes | H34: A value that represents the tax lot being a long or short position. Valid Values: L = Long S = Short | M34: =VLOOKUP(A34,Model!C$2:J$93,2,FALSE)=C34 -> TRUE | O34: =VLOOKUP(A34,Model!C$2:J$93,3,FALSE)=H34 -> FALSE | P34: =VLOOKUP(A34,Model!C$2:J$93,3,FALSE) -> A value that represents the tax lot being a long or short position. Valid Values: L = Long S = Short MAXIT Source: TAXLOT_DTL_OPN.LONG_SHRT_POS rjt sOURCE: TAX_LOT_OPN_MSTR.POS_LONG_SHRT_CODE | Q34: =VLOOKUP(A34,Model!C$2:J$93,8,FALSE) -> 32 | R34: =VLOOKUP(C34,Table!A$2:F$98,1,FALSE)=C34 -> TRUE | S34: =VLOOKUP(SUBSTITUTE(A34," ","_"),View!A$2:I$106,1,FALSE) -> LONG_SHORT_POSITION_CODE | T34: TAXLOT_STG_OWNER | U34: OPN_TAX_LOTS_NONBKR_TGT | V34: POS_LONG_SHRT_CODE | W34: VARCHAR2(1) | X34: Yes
A35: Loss Not Allowed Flag | C35: LOSS_NOT_ALWD_F | D35: VARCHAR2(1) | E35: Yes | F35: Character Varying(1) | G35: Yes | H35: The loss on a transaction that is disallowed for tax purposes because it is part of a wash sale. | M35: =VLOOKUP(A35,Model!C$2:J$93,2,FALSE)=C35 -> TRUE | O35: =VLOOKUP(A35,Model!C$2:J$93,3,FALSE)=H35 -> FALSE | P35: =VLOOKUP(A35,Model!C$2:J$93,3,FALSE) -> MAXIT Source: TAXLOT_DTL_OPN.LOSS_NOT_ALLOWED RJT Source: None In a cash and stock merger the client may not be allowed to take a loss on the disposition of the old stock, any losses are rolled into the new stock. Merger / Acquisition or Corporate Inversion Transactions. This field is currently used on Closed Tax Lot Tax Reporting at this time. Values: N = No, Loss allowed Y = Yes, No Loss allowed | Q35: =VLOOKUP(A35,Model!C$2:J$93,8,FALSE) -> 33 | R35: =VLOOKUP(C35,Table!A$2:F$98,1,FALSE)=C35 -> TRUE | S35: =VLOOKUP(SUBSTITUTE(A35," ","_"),View!A$2:I$106,1,FALSE) -> LOSS_NOT_ALLOWED_FLAG | V35: NULL | W35: VARCHAR2(1) | X35: Yes
A36: Life To Date Market Discount | C36: LIFE_TO_DTD_MKT_DCN | D36: NUMBER(22,6) | E36: Yes | F36: NUMERIC(22,6) | G36: Yes | H36: Life-to-Date Market Discount calculated from the open date or the last adjustment date of the fixed income security | M36: =VLOOKUP(A36,Model!C$2:J$93,2,FALSE)=C36 -> TRUE | O36: =VLOOKUP(A36,Model!C$2:J$93,3,FALSE)=H36 -> FALSE | P36: =VLOOKUP(A36,Model!C$2:J$93,3,FALSE) -> Life to date market discount amount_x000D_ _x000D_ Total market discount accrued since the purchase of the bond_x000D_ _x000D_ MAXIT Source: TAXLOT_DTL_OPN.LTD_MKT_DISCOUNT | Q36: =VLOOKUP(A36,Model!C$2:J$93,8,FALSE) -> 34 | R36: =VLOOKUP(C36,Table!A$2:F$98,1,FALSE)=C36 -> TRUE | S36: =VLOOKUP(SUBSTITUTE(A36," ","_"),View!A$2:I$106,1,FALSE) -> LIFE_TO_DATE_MARKET_DISCOUNT | V36: NULL | W36: NUMBER(22,6) | X36: Yes
A37: Missing Cost Basis Flag | C37: MISS_COST_BSS_F | D37: VARCHAR2(1) | E37: Yes | F37: Character Varying(1) | G37: Yes | H37: Indicates that Cost basis is not available for this position | M37: =VLOOKUP(A37,Model!C$2:J$93,2,FALSE)=C37 -> TRUE | O37: =VLOOKUP(A37,Model!C$2:J$93,3,FALSE)=H37 -> FALSE | P37: =VLOOKUP(A37,Model!C$2:J$93,3,FALSE) -> Indicates that Cost basis is not available for this position MAXIT Source: TAXLOT_DTL_OPN.MISS_COST_F RJT Source: TAX_LOT_OPN_MSTR.MISS_COST_F | Q37: =VLOOKUP(A37,Model!C$2:J$93,8,FALSE) -> 35 | R37: =VLOOKUP(C37,Table!A$2:F$98,1,FALSE)=C37 -> TRUE | S37: =VLOOKUP(SUBSTITUTE(A37," ","_"),View!A$2:I$106,1,FALSE) -> MISSING_COST_BASIS_FLAG | T37: TAXLOT_STG_OWNER | U37: OPN_TAX_LOTS_NONBKR_TGT | V37: MISS_COST_F | W37: VARCHAR2(1) | X37: Yes | Y37: CASE WHEN (TAX_LOT_OPN_MSTR.MISS_COST_F = 'Y' OR TAX_LOT_OPN_MSTR.null_bss_f = 'Y') THEN 'Y' ELSE 'N' END
A38: Adjusted Cost Not Accurate Flag | C38: ADJ_COST_NOT_ACRT_F | D38: VARCHAR2(1) | E38: Yes | F38: Character Varying(1) | G38: Yes | H38: Indcates that Adjusted Cost is not accurate due to missing cost on atleast one sublot Source:NULL_F Y = YES – At least one of the associated average cost records is missing average cost N = NO – None of the associated average cost records are missing average cost | M38: =VLOOKUP(A38,Model!C$2:J$93,2,FALSE)=C38 -> TRUE | O38: =VLOOKUP(A38,Model!C$2:J$93,3,FALSE)=H38 -> FALSE | P38: =VLOOKUP(A38,Model!C$2:J$93,3,FALSE) -> MAXIT Source: TAXLOT_DTL_OPN.NULL_F RJT Source: TAX_LOT_OPN_MSTR.NULL_BSS_F Indcates that Adjusted Cost is not accurate due to missing cost on atleast one sublot Source:NULL_F Y = YES ? At least one of the associated average cost records is missing average cost N = NO ? None of the associated average cost records are missing average cost | Q38: =VLOOKUP(A38,Model!C$2:J$93,8,FALSE) -> 36 | R38: =VLOOKUP(C38,Table!A$2:F$98,1,FALSE)=C38 -> TRUE | S38: =VLOOKUP(SUBSTITUTE(A38," ","_"),View!A$2:I$106,1,FALSE) -> ADJUSTED_COST_NOT_ACCURATE_FLAG | T38: TAXLOT_STG_OWNER | U38: OPN_TAX_LOTS_NONBKR_TGT | V38: NULL_BSS_F | W38: VARCHAR2(1) | X38: Yes
A39: Open Price Factor | C39: OPN_PRC_FCTR | D39: NUMBER(22,6) | E39: Yes | F39: NUMERIC(22,6) | G39: Yes | H39: Price_factor of opening transaction Used for factored bonds RJT Source: TAX_LOT_OPN_MSTR.NML_CCY_OPN_PRC_FCTR | M39: =VLOOKUP(A39,Model!C$2:J$93,2,FALSE)=C39 -> TRUE | O39: =VLOOKUP(A39,Model!C$2:J$93,3,FALSE)=H39 -> FALSE | P39: =VLOOKUP(A39,Model!C$2:J$93,3,FALSE) -> Price_factor of opening transaction Used for factored bonds MAXIT Source: TAXLOT_DTL_OPN.OPN_FCTR RJT Source: TAX_LOT_OPN_MSTR.NML_CCY_OPN_PRC_FCTR | Q39: =VLOOKUP(A39,Model!C$2:J$93,8,FALSE) -> 37 | R39: =VLOOKUP(C39,Table!A$2:F$98,1,FALSE)=C39 -> TRUE | S39: =VLOOKUP(SUBSTITUTE(A39," ","_"),View!A$2:I$106,1,FALSE) -> OPEN_PRICE_FACTOR | T39: TAXLOT_STG_OWNER | U39: OPN_TAX_LOTS_NONBKR_TGT | V39: SBC_OPN_PRC_FCTR | W39: NUMBER(22,6) | X39: Yes | Y39: OPN_FCTR OPN_PRC_FCTR, case when (CCY_CODE ='USD' or (EXG_RATE is NULL OR EXG_RATE = 0)) THEN OPN_FCTR ELSE OPN_FCTR * EXG_RATE END SBC_OPN_PRC_FCTR
A40: Open Transaction Event Type | C40: OPN_TXN_EV_TP | D40: VARCHAR2(40) | E40: Yes | F40: Character Varying(40) | G40: Yes | H40: RJT Source: TAX_LOT_OPN_MSTR.TAX_LOT_TXN_EV_TP_ID For open and closed lots, this field includes the 'event' of the opening transaction | M40: =VLOOKUP(A40,Model!C$2:J$93,2,FALSE)=C40 -> TRUE | O40: =VLOOKUP(A40,Model!C$2:J$93,3,FALSE)=H40 -> FALSE | P40: =VLOOKUP(A40,Model!C$2:J$93,3,FALSE) -> Source: TAXLOT_DTL_OPN.OPN_TXN_EV_ID RJT Source: TAX_LOT_OPN_MSTR.TAX_LOT_TXN_EV_TP_ID For open lots ? Maxit Event ID For closed lots ? Maxit Event ID of the closing transaction For open and closed lots, this field includes the 'event' of the opening transaction This is a Maxit created Event Name to identify tax lots and create associations between tax lots " | Q40: =VLOOKUP(A40,Model!C$2:J$93,8,FALSE) -> 38 | R40: =VLOOKUP(C40,Table!A$2:F$98,1,FALSE)=C40 -> TRUE | S40: =VLOOKUP(SUBSTITUTE(A40," ","_"),View!A$2:I$106,1,FALSE) -> OPEN_TRANSACTION_EVENT_TYPE | T40: CCAL_REPL_OWNER | U40: CL_VAL | V40: CL_VAL_NM | W40: VARCHAR2(40) | X40: Yes | Y40: Use TAX_LOT_TXN_EV_TP_ID in CL_VAL_ID in CL_VAL table and pick CL_VAL_NM where CL_SCM_CD= 86
A41: Cost Amount | C41: COST_AMT | D41: NUMBER(22,6) | E41: Yes | F41: NUMERIC(22,6) | G41: Yes | H41: Original total purchase cost of the instrument Buy, the net amount is shown. Sell, cost sold for a sell is displayed. Note: This field cannot be used currently as it is not prorated or adjusted for changes/actions/partial sells where a change in quantity is made. | M41: =VLOOKUP(A41,Model!C$2:J$93,2,FALSE)=C41 -> TRUE | O41: =VLOOKUP(A41,Model!C$2:J$93,3,FALSE)=H41 -> FALSE | P41: =VLOOKUP(A41,Model!C$2:J$93,3,FALSE) -> Original total purchase cost of the instrument Buy, the net amount is shown. Sell, cost sold for a sell is displayed. Note: This field cannot be used currently as it is not prorated or adjusted for changes/actions/partial sells where a change in quantity is made. MAXIT Source: TAXLOT_DTL_OPN.ORIG_COST RJT Source:TAX_LOT_OPN_ASOF.NML_ASOF_CRN_COST_AMT | Q41: =VLOOKUP(A41,Model!C$2:J$93,8,FALSE) -> 39 | R41: =VLOOKUP(C41,Table!A$2:F$98,1,FALSE)=C41 -> TRUE | S41: =VLOOKUP(SUBSTITUTE(A41," ","_"),View!A$2:I$106,1,FALSE) -> COST_AMOUNT | T41: TAXLOT_STG_OWNER | U41: OPN_TAX_LOTS_NONBKR_TGT | V41: NML_ASOF_CRN_COST_AMT | W41: NUMBER(22,6) | X41: Yes | Y41: ORIG_COST COST_AMT, case when (CCY_CODE ='USD' or (EXG_RATE is NULL OR EXG_RATE = 0)) THEN ORIG_COST ELSE ORIG_COST * EXG_RATE END SBC_COST_AMT
A42: Original Event Type | C42: ORIG_EV_TP | D42: VARCHAR2(32) | E42: Yes | F42: Character Varying(32) | G42: Yes | H42: Opening transaction original event ID. Used when opening transaction event ID represents a corporate action, in which case the original event ID (such as DRIP BUY, gift, or inheritance, etc. is more important)Source: ORIG_EV_ID | M42: =VLOOKUP(A42,Model!C$2:J$93,2,FALSE)=C42 -> TRUE | O42: =VLOOKUP(A42,Model!C$2:J$93,3,FALSE)=H42 -> FALSE | P42: =VLOOKUP(A42,Model!C$2:J$93,3,FALSE) -> MAAXIT Source: ORIG_EV_ID Opening transaction original event ID. Used when opening transaction event ID represents a corporate action, in which case the original event ID (such as DRIP BUY, gift, or inheritance, etc. is more important) Maxit ID of the original opening transaction (i.e. would be the id associated with a buy should a reorg/corp action come along and close out that open and create new open with new opening transaction id). Source: ORIG_EV_ID | Q42: =VLOOKUP(A42,Model!C$2:J$93,8,FALSE) -> 40 | R42: =VLOOKUP(C42,Table!A$2:F$98,1,FALSE)=C42 -> TRUE | S42: =VLOOKUP(SUBSTITUTE(A42," ","_"),View!A$2:I$106,1,FALSE) -> ORIGINAL_EVENT_TYPE | T42: TAXLOT_STG_OWNER | U42: OPN_TAX_LOTS_NONBKR_TGT | W42: VARCHAR2(32) | X42: Yes | Y42: its always NULL
A43: Original Price | C43: ORIG_PRC | D43: NUMBER(22,6) | E43: Yes | F43: NUMERIC(22,6) | G43: Yes | H43: Per share price of the opening tax lot.big_prc of the Buy/open short. Will be populated for a sell with opening price. Note: This field cannot be used currently as it is not prorated or adjusted for changes/actions/partial sells where a change in quantity is made. | M43: =VLOOKUP(A43,Model!C$2:J$93,2,FALSE)=C43 -> TRUE | O43: =VLOOKUP(A43,Model!C$2:J$93,3,FALSE)=H43 -> FALSE | P43: =VLOOKUP(A43,Model!C$2:J$93,3,FALSE) -> Per share price of the opening tax lot. big_prc of the Buy/open short. Will be populated for a sell with opening price. Note: This field cannot be used currently as it is not prorated or adjusted for changes/actions/partial sells where a change in quantity is made. MAXIT Source: TAXLOT_DTL_OPN.ORIG_PRC RJT Source: TAX_LOT_OPN_MSTR.NML_CCY_ORIG_PRC | Q43: =VLOOKUP(A43,Model!C$2:J$93,8,FALSE) -> 41 | R43: =VLOOKUP(C43,Table!A$2:F$98,1,FALSE)=C43 -> TRUE | S43: =VLOOKUP(SUBSTITUTE(A43," ","_"),View!A$2:I$106,1,FALSE) -> ORIGINAL_PRICE | T43: TAXLOT_STG_OWNER | U43: OPN_TAX_LOTS_NONBKR_TGT | V43: SBC_ORIG_PRC | W43: NUMBER(22,6) | X43: Yes | Y43: ORIG_PRC, case when (CCY_CODE ='USD' or (EXG_RATE is NULL OR EXG_RATE = 0)) THEN ORIG_PRC ELSE ORIG_PRC * EXG_RATE END SBC_ORIG_PRC
A44: Original Proceed | C44: ORIG_PROCD | D44: NUMBER(22,6) | E44: Yes | F44: NUMERIC(22,6) | G44: Yes | H44: Net_amount of asgn sell before adding premium. Note: This field cannot be used currently as it is not prorated or adjusted for changes/actions/partial sells where a change in quantity is made. | M44: =VLOOKUP(A44,Model!C$2:J$93,2,FALSE)=C44 -> TRUE | O44: =VLOOKUP(A44,Model!C$2:J$93,3,FALSE)=H44 -> FALSE | P44: =VLOOKUP(A44,Model!C$2:J$93,3,FALSE) -> Net_amount of asgn sell before adding premium. Note: This field cannot be used currently as it is not prorated or adjusted for changes/actions/partial sells where a change in quantity is made. MAXIT Source: TAXLOT_DTL_OPN.ORIG_PROCD RJT Source: TAX_LOT_OPN_MSTR.NML_CCY_ORIG_PROCD_AMT | Q44: =VLOOKUP(A44,Model!C$2:J$93,8,FALSE) -> 42 | R44: =VLOOKUP(C44,Table!A$2:F$98,1,FALSE)=C44 -> TRUE | S44: =VLOOKUP(SUBSTITUTE(A44," ","_"),View!A$2:I$106,1,FALSE) -> ORIGINAL_PROCEED | T44: TAXLOT_STG_OWNER | U44: OPN_TAX_LOTS_NONBKR_TGT | V44: SBC_ORIG_PROCD_AMT | W44: NUMBER(22,6) | X44: Yes | Y44: ORIG_PROCD, case when (CCY_CODE ='USD' or (EXG_RATE is NULL OR EXG_RATE = 0)) THEN ORIG_PROCD ELSE ORIG_PROCD * EXG_RATE END SBC_ORIG_PROCD
A45: Original Transaction Type Code | C45: ORIG_TXN_TP_CD | D45: VARCHAR2(32) | E45: Yes | F45: Character Varying(32) | G45: Yes | H45: Opening transaction original TRAN TYPE ID. Used when opening transaction tran type represents a corporate action, in which case the original tran type (such as DRP, GFT, or INH, etc. is more important) Additional Notes: The purpose of this field is to preserve the TRAN_TYPE with which the position was opened. As opposed to TRAN_TYPE, this field survives corporate actions and wash sale sub-lot allocation. One of the important use cases of ORIGINAL_TRAN_TYPE is alongside of transfers such as ACATs, where the values of INH and GFT indicate gift or inheritance. It should be noted that lots created due to corporate actions on inherited or gifted positions will have ORIGINAL_TRAN_TYPE of INH and GFT, and the TRAN_TYPE set to that of the corporate action. This is a Maxit specific code that describes the category of transaction/action that created the open tax lot. Note: Inherited = INH Inherited than Gifted = ITG - NEW TFS Requirement 195137 Gifted = GFT existing values: BUY, INH, DRP, ACT, XCH, SED, ATF, RCV, BTO, SHS, EXC, GFT, SCC, STO, CCG, ASN, SPN, RSP, MRG, SDV, RTS, DVR, BPR, WSH, ACQ, OID, MDI, NQSI, LIQ | M45: =VLOOKUP(A45,Model!C$2:J$93,2,FALSE)=C45 -> TRUE | O45: =VLOOKUP(A45,Model!C$2:J$93,3,FALSE)=H45 -> FALSE | P45: =VLOOKUP(A45,Model!C$2:J$93,3,FALSE) -> MAXIT Source: TAXLOT_DTL_OPN.ORIG_TXN_TP RJT Source:TAX_LOT_OPN_MSTR.ORIG_TAX_LOT_TXN_TP_ID Opening transaction original TRAN TYPE ID. Used when opening transaction tran type represents a corporate action, in which case the original tran type (such as DRP, GFT, or INH, etc. is more important) Additional Notes: The purpose of this field is to preserve the TRAN_TYPE with which the position was opened. As opposed to TRAN_TYPE, this field survives corporate actions and wash sale sub-lot allocation. One of the important use cases of ORIGINAL_TRAN_TYPE is alongside of transfers such as ACATs, where the values of INH and GFT indicate gift or inheritance. It should be noted that lots created due to corporate actions on inherited or gifted positions will have ORIGINAL_TRAN_TYPE of INH and GFT, and the TRAN_TYPE set to that of the corporate action. This is a Maxit specific code that describes the category of transaction/action that created the open tax lot. Note: Inherited = INH Inherited than Gifted = ITG - NEW TFS Requirement 195137 Gifted = GFT source: ORIG_TXN_TP existing values: BUY, INH, DRP, ACT, XCH, SED, ATF, RCV, BTO, SHS, EXC, GFT, SCC, STO, CCG, ASN, SPN, RSP, MRG, SDV, RTS, DVR, BPR, WSH, ACQ, OID, MDI, NQSI, LIQ | Q45: =VLOOKUP(A45,Model!C$2:J$93,8,FALSE) -> 43 | R45: =VLOOKUP(C45,Table!A$2:F$98,1,FALSE)=C45 -> TRUE | S45: =VLOOKUP(SUBSTITUTE(A45," ","_"),View!A$2:I$106,1,FALSE) -> ORIGINAL_TRANSACTION_TYPE_CODE | T45: TAXLOT_STG_OWNER | U45: OPN_TAX_LOTS_NONBKR_TGT | W45: VARCHAR2(32) | X45: Yes | Y45: its always NULL
A46: Premium Amount | C46: PREM_AMT | D46: NUMBER(22,6) | E46: Yes | F46: NUMERIC(22,6) | G46: Yes | H46: The option premium amount that is added to the underlying stock when an option is assigned to the holder. | M46: =VLOOKUP(A46,Model!C$2:J$93,2,FALSE)=C46 -> TRUE | O46: =VLOOKUP(A46,Model!C$2:J$93,3,FALSE)=H46 -> FALSE | P46: =VLOOKUP(A46,Model!C$2:J$93,3,FALSE) -> MAXIT Source:TAXLOT_DTL_OPN. PREMIUM RJT Source: None option premium amount added to the underlying stock when an option is assigned to the holder. | Q46: =VLOOKUP(A46,Model!C$2:J$93,8,FALSE) -> 44 | R46: =VLOOKUP(C46,Table!A$2:F$98,1,FALSE)=C46 -> TRUE | S46: =VLOOKUP(SUBSTITUTE(A46," ","_"),View!A$2:I$106,1,FALSE) -> PREMIUM_AMOUNT | V46: NULL | W46: NUMBER(22,6) | X46: Yes
A47: Quantity | C47: QTY | D47: NUMBER(22,6) | E47: Yes | F47: NUMERIC(22,6) | G47: Yes | H47: Contains the total shares / PAR value for the open or closed tax lot position. Lot quantity per Maxit When long_short_position = S, always set to (absolute value * -1) When long_short_position = L, always set to absolute value RJT Source: TAX_LOT_OPN_ASOF.TAX_LOT_ASOF_QTY | M47: =VLOOKUP(A47,Model!C$2:J$93,2,FALSE)=C47 -> TRUE | O47: =VLOOKUP(A47,Model!C$2:J$93,3,FALSE)=H47 -> FALSE | P47: =VLOOKUP(A47,Model!C$2:J$93,3,FALSE) -> Contains the total shares / PAR value for the open or closed tax lot position. Lot quantity per Maxit When long_short_position = S, always set to (absolute value * -1) When long_short_position = L, always set to absolute value MAXIT Source: TAXLOT_DTL_OPN.QTY RJT Source: TAX_LOT_OPN_ASOF.TAX_LOT_ASOF_QTY | Q47: =VLOOKUP(A47,Model!C$2:J$93,8,FALSE) -> 45 | R47: =VLOOKUP(C47,Table!A$2:F$98,1,FALSE)=C47 -> TRUE | S47: =VLOOKUP(SUBSTITUTE(A47," ","_"),View!A$2:I$106,1,FALSE) -> QUANTITY | T47: TAXLOT_STG_OWNER | U47: OPN_TAX_LOTS_NONBKR_TGT | V47: TAX_LOT_ASOF_QTY | W47: NUMBER(22,6) | X47: Yes
A48: Source Record Type Code | C48: SRC_RCRD_TP_CD | D48: VARCHAR2(40) | E48: Yes | F48: Character Varying(40) | G48: Yes | H48: RJT Source: TAX_LOT_OPN_MSTR SRC_RCRD_TP_ID Y= Tax Lot Record Type specific to Raymond James Trust | M48: =VLOOKUP(A48,Model!C$2:J$93,2,FALSE)=C48 -> TRUE | O48: =VLOOKUP(A48,Model!C$2:J$93,3,FALSE)=H48 -> FALSE | P48: =VLOOKUP(A48,Model!C$2:J$93,3,FALSE) -> MAXIT Source: CCAL_TAXLOT_OWNER.TAXLOT_DTL_OPN/CLS.RCRD_TP RJT Source: TAX_LOT_OPN_MSTR SRC_RCRD_TP_ID (CCAL_OWNER.RCRD_TP) values A = Assigned ? Associated with the Closed Tax Lot ONLY B = Buy ? Associated with the Open Tax Lot ONLY C = Cover Short ? Associated with Closed Tax Lot ONLY D = Deliver ? Associated with Closed Tax Lot ONLY E = Expired ? Associated with Closed Tax Lot ONLY H = Transfer of a Short Deliver ? Associated with the Open Tax Lot ONLY L = Short Sell ? Associated with the Open Tax Lot ONLY M = Redemption ? Associated with Closed Tax Lot ONLY R = Receive Record ? Associated with either Open or Closed Tax Lot S = Sell ? Associated with Closed Tax Lot ONLY V = Dividend Reinvestment ? Associated with the Open Tax Lot ONLY Z = record type is not applicable to that type of record | Q48: =VLOOKUP(A48,Model!C$2:J$93,8,FALSE) -> 46 | R48: =VLOOKUP(C48,Table!A$2:F$98,1,FALSE)=C48 -> TRUE | S48: =VLOOKUP(SUBSTITUTE(A48," ","_"),View!A$2:I$106,1,FALSE) -> SOURCE_RECORD_TYPE_CODE | U48: CL_VAL | V48: CL_VAL_CD | W48: VARCHAR2(40) | X48: Yes | Y48: Use SRC_RCRD_TP_ID in CL_VAL and use- CL_VAL_CD
A49: Reinvestment Lot Flag | C49: RVST_LOT_F | D49: VARCHAR2(1) | E49: Yes | F49: Character Varying(1) | G49: Yes | H49: Re-investment indicator linked to Dividend Reinvestment Plan (DRIP) logic. Indicates whether the lot is eligible to be included in the position’s average cost. | M49: =VLOOKUP(A49,Model!C$2:J$93,2,FALSE)=C49 -> TRUE | O49: =VLOOKUP(A49,Model!C$2:J$93,3,FALSE)=H49 -> FALSE | P49: =VLOOKUP(A49,Model!C$2:J$93,3,FALSE) -> MAXIT Source: TAXLOT_DTL_OPN.RVST_F RJT Source: TAX_LOT_OPN_MSTR.RVST_F For MAXIT it is RJ Derived When original_tran_type = DRP, set to Y ELSE set to N " | Q49: =VLOOKUP(A49,Model!C$2:J$93,8,FALSE) -> 47 | R49: =VLOOKUP(C49,Table!A$2:F$98,1,FALSE)=C49 -> TRUE | S49: =VLOOKUP(SUBSTITUTE(A49," ","_"),View!A$2:I$106,1,FALSE) -> REINVESTMENT_LOT_FLAG | T49: TAXLOT_STG_OWNER | U49: OPN_TAX_LOTS_NONBKR_TGT | V49: RVST_F | W49: VARCHAR2(1) | X49: Yes
A50: Settlement Date | C50: SD | D50: DATE | E50: Yes | F50: Timestamp without time zone | G50: Yes | H50: Settlement date of Open/close transaction supplied by RJ. | M50: =VLOOKUP(A50,Model!C$2:J$93,2,FALSE)=C50 -> TRUE | O50: =VLOOKUP(A50,Model!C$2:J$93,3,FALSE)=H50 -> FALSE | P50: =VLOOKUP(A50,Model!C$2:J$93,3,FALSE) -> Settlement date of Open/close transaction supplied by RJ or created by Maxit for corporate actions. MAXIT Source: TAXLOT_DTL_OPN.SD RJT Source: TAX_LOT_OPN_MSTR.SD | Q50: =VLOOKUP(A50,Model!C$2:J$93,8,FALSE) -> 48 | R50: =VLOOKUP(C50,Table!A$2:F$98,1,FALSE)=C50 -> TRUE | S50: =VLOOKUP(SUBSTITUTE(A50," ","_"),View!A$2:I$106,1,FALSE) -> SETTLEMENT_DATE | T50: TAXLOT_STG_OWNER | U50: OPN_TAX_LOTS_NONBKR_TGT | V50: SD | W50: DATE | X50: Yes
A51: Trade Number | C51: TRD_NUM | D51: VARCHAR2(80) | E51: Yes | F51: Character Varying(80) | G51: Yes | H51: Client specific transaction no. | M51: =VLOOKUP(A51,Model!C$2:J$93,2,FALSE)=C51 -> TRUE | O51: =VLOOKUP(A51,Model!C$2:J$93,3,FALSE)=H51 -> FALSE | P51: =VLOOKUP(A51,Model!C$2:J$93,3,FALSE) -> MAXIT Source: TAXLOT_DTL_OPN.TRD_NUM | Q51: =VLOOKUP(A51,Model!C$2:J$93,8,FALSE) -> 50 | R51: =VLOOKUP(C51,Table!A$2:F$98,1,FALSE)=C51 -> TRUE | S51: =VLOOKUP(SUBSTITUTE(A51," ","_"),View!A$2:I$106,1,FALSE) -> TRADE_NUMBER | T51: TAXLOT_STG_OWNER | U51: OPN_TAX_LOTS_NONBKR_TGT | V51: TRD_NUM | W51: VARCHAR2(80) | X51: Yes
A52: Transaction Initiate Date | C52: TXN_INTT_DT | D52: DATE | E52: Yes | F52: Timestamp without time zone | G52: Yes | H52: This is the date transfer is made. | M52: =VLOOKUP(A52,Model!C$2:J$93,2,FALSE)=C52 -> TRUE | O52: =VLOOKUP(A52,Model!C$2:J$93,3,FALSE)=H52 -> FALSE | P52: =VLOOKUP(A52,Model!C$2:J$93,3,FALSE) -> MAXIT Source:TAXLOT_DTL_OPN.TXN_INIT_DT_x000D_ RJT Source: TAX_LOT_OPN_MSTR.TXN_INTT_DT_x000D_ _x000D_ | Q52: =VLOOKUP(A52,Model!C$2:J$93,8,FALSE) -> 51 | R52: =VLOOKUP(C52,Table!A$2:F$98,1,FALSE)=C52 -> TRUE | S52: =VLOOKUP(SUBSTITUTE(A52," ","_"),View!A$2:I$106,1,FALSE) -> TRANSACTION_INITIATE_DATE | T52: TAXLOT_STG_OWNER | U52: OPN_TAX_LOTS_NONBKR_TGT | V52: TXN_INIT_DT | W52: DATE | X52: Yes
A53: Transaction Type Code | C53: TXN_TP_CD | D53: VARCHAR2(40) | E53: Yes | F53: Character Varying(40) | G53: Yes | H53: Code assigned to each transaction type. Transaction types offer a broad classification of the transaction Base on defined industry/line-of-business definitions such as a 'Buy', 'Deposit', 'Merger', etc. | M53: =VLOOKUP(A53,Model!C$2:J$93,2,FALSE)=C53 -> TRUE | O53: =VLOOKUP(A53,Model!C$2:J$93,3,FALSE)=H53 -> FALSE | P53: =VLOOKUP(A53,Model!C$2:J$93,3,FALSE) -> MAXIT Source: TAXLOT_DTL_OPN.TXN_TP RJT Source: TAX_LOT_OPN_MSTR.ORIG_TAX_LOT_TXN_TP_ID | Q53: =VLOOKUP(A53,Model!C$2:J$93,8,FALSE) -> 52 | R53: =VLOOKUP(C53,Table!A$2:F$98,1,FALSE)=C53 -> TRUE | S53: =VLOOKUP(SUBSTITUTE(A53," ","_"),View!A$2:I$106,1,FALSE) -> TRANSACTION_TYPE_CODE | T53: TAXLOT_STG_OWNER | U53: OPN_TAX_LOTS_NONBKR_TGT | W53: VARCHAR2(40) | X53: Yes | Y53: its always NULL
A54: Unit Cost | C54: UC | D54: NUMBER(22,6) | E54: Yes | F54: NUMERIC(22,6) | G54: Yes | H54: Opening price per share | M54: =VLOOKUP(A54,Model!C$2:J$93,2,FALSE)=C54 -> TRUE | O54: =VLOOKUP(A54,Model!C$2:J$93,3,FALSE)=H54 -> FALSE | P54: =VLOOKUP(A54,Model!C$2:J$93,3,FALSE) -> MAXIT Source: TAXLOT_DTL_OPN.UC RJT Source: TAX_LOT_OPN_ASOF.NML_CCY_ASOF_PER_UC_AMT | Q54: =VLOOKUP(A54,Model!C$2:J$93,8,FALSE) -> 53 | R54: =VLOOKUP(C54,Table!A$2:F$98,1,FALSE)=C54 -> TRUE | S54: =VLOOKUP(SUBSTITUTE(A54," ","_"),View!A$2:I$106,1,FALSE) -> UNIT_COST | T54: TAXLOT_STG_OWNER | U54: OPN_TAX_LOTS_NONBKR_TGT | V54: SBC_OPN_PER_UC_AMT | W54: NUMBER(22,6) | X54: Yes | Y54: UC, case when (CCY_CODE ='USD' or (EXG_RATE is NULL OR EXG_RATE = 0)) THEN UC ELSE UC * EXG_RATE END SBC_UC
A55: System Base Currency Unit Cost | C55: SBC_UC | D55: NUMBER(22,6) | E55: Yes | F55: NUMERIC(22,6) | G55: Yes | H55: Unit cost of a security denominated based on currency used in sysytem. | M55: =VLOOKUP(A55,Model!C$2:J$93,2,FALSE)=C55 -> TRUE | O55: =VLOOKUP(A55,Model!C$2:J$93,3,FALSE)=H55 -> FALSE | P55: =VLOOKUP(A55,Model!C$2:J$93,3,FALSE) -> MAXIT Source: TAXLOT_DTL_OPN.UC RJT Source: TAX_LOT_OPN_ASOF.NML_CCY_ASOF_PER_UC_AMT | Q55: =VLOOKUP(A55,Model!C$2:J$93,8,FALSE) -> 54 | R55: =VLOOKUP(C55,Table!A$2:F$98,1,FALSE)=C55 -> TRUE | S55: =VLOOKUP(SUBSTITUTE(A55," ","_"),View!A$2:I$106,1,FALSE) -> SYSTEM_BASE_CURRENCY_UNIT_COST | T55: TAXLOT_STG_OWNER | U55: OPN_TAX_LOTS_NONBKR_TGT | V55: SBC_OPN_PER_UC_AMT | W55: NUMBER(22,6) | X55: Yes | Y55: UC, case when (CCY_CODE ='USD' or (EXG_RATE is NULL OR EXG_RATE = 0)) THEN UC ELSE UC * EXG_RATE END SBC_UC
A56: Wash Sale Flag | C56: WASH_SALE_F | D56: VARCHAR2(1) | E56: Yes | F56: Character Varying(1) | G56: Yes | H56: Flag designates when a Wash Sale, a transaction where an investor sells a losing security to claim a capital loss, only to repurchase it again for a bargain. | M56: =VLOOKUP(A56,Model!C$2:J$93,2,FALSE)=C56 -> TRUE | O56: =VLOOKUP(A56,Model!C$2:J$93,3,FALSE)=H56 -> FALSE | P56: =VLOOKUP(A56,Model!C$2:J$93,3,FALSE) -> MAXIT Source: TAXLOT_DTL_OPN.WASH_SALE_IND RJT Source: TAX_LOT_OPN_MSTR.WASH_SALE_F WASH_SALE_IND on Source. Y= Wash Sale Sublot | Q56: =VLOOKUP(A56,Model!C$2:J$93,8,FALSE) -> 55 | R56: =VLOOKUP(C56,Table!A$2:F$98,1,FALSE)=C56 -> TRUE | S56: =VLOOKUP(SUBSTITUTE(A56," ","_"),View!A$2:I$106,1,FALSE) -> WASH_SALE_FLAG | T56: TAXLOT_STG_OWNER | U56: OPN_TAX_LOTS_NONBKR_TGT | V56: WASH_SALE_F | W56: VARCHAR2(1) | X56: Yes
A57: Zero Cost Basis Flag | C57: ZERO_COST_BSS_F | D57: VARCHAR2(2) | E57: Yes | F57: Character Varying(2) | G57: Yes | H57: This indicates whether a tax lot without cost basis is just missing or it is a true zero basis. | M57: =VLOOKUP(A57,Model!C$2:J$93,2,FALSE)=C57 -> TRUE | O57: =VLOOKUP(A57,Model!C$2:J$93,3,FALSE)=H57 -> FALSE | P57: =VLOOKUP(A57,Model!C$2:J$93,3,FALSE) -> MAXIT Source TAXLOT_DTL_OPN.ZERO_BSS_IND RJT Source: TAX_LOT_OPN_MSTR.ZERO_BSS_IND_F | Q57: =VLOOKUP(A57,Model!C$2:J$93,8,FALSE) -> 56 | R57: =VLOOKUP(C57,Table!A$2:F$98,1,FALSE)=C57 -> TRUE | S57: =VLOOKUP(SUBSTITUTE(A57," ","_"),View!A$2:I$106,1,FALSE) -> ZERO_COST_BASIS_FLAG | T57: TAXLOT_STG_OWNER | U57: OPN_TAX_LOTS_NONBKR_TGT | V57: ZERO_BSS_IND_F | W57: VARCHAR2(2) | X57: Yes
A58: Wash Sale Type | C58: WASH_SALE_TP | D58: VARCHAR2(500) | E58: Yes | F58: Character Varying(500) | G58: Yes | H58: The Boolean value (Y/N) that indicates whether or not a Tax Lot Closed open portion of transaction is a wash sale sublot – ‘Y’ Otherwise ‘N’ | M58: =VLOOKUP(A58,Model!C$2:J$93,2,FALSE)=C58 -> TRUE | O58: =VLOOKUP(A58,Model!C$2:J$93,3,FALSE)=H58 -> FALSE | P58: =VLOOKUP(A58,Model!C$2:J$93,3,FALSE) -> Wash Sale Type from SRD | Q58: =VLOOKUP(A58,Model!C$2:J$93,8,FALSE) -> 57 | R58: =VLOOKUP(C58,Table!A$2:F$98,1,FALSE)=C58 -> TRUE | S58: =VLOOKUP(SUBSTITUTE(A58," ","_"),View!A$2:I$106,1,FALSE) -> WASH_SALE_TYPE | V58: NULL | Y58: (CASE WHEN TAX_LOT_OPN_MSTR.WASH_SALE_IND ='Y' AND TAX_LOT_OPN_MSTR.DISALWD_WASHSALE_AMT = 0 THEN 'CBW' WHEN TAX_LOT_OPN_MSTR.WASH_SALE_IND ='Y' AND TAX_LOT_OPN_MSTR.DISALWD_WASHSALE_AMT > 0 THEN 'BOTHW' WHEN TAX_LOT_OPN_MSTR.WASH_SALE_IND <> 'Y' AND TAX_LOT_OPN_MSTR.DISALWD_WASHSALE_AMT > 0 THEN 'GLW' END) AS WASH_SALE_TP
A59: System Base Currency Disallowed Wash Sale Amount | C59: SBC_DISALWD_WASH_SALE_AMT | D59: NUMBER(22,6) | E59: Yes | F59: NUMERIC(22,6) | G59: Yes | H59: This is the amount of the losses that are disallowed by wash sale rules. This value will be on the sells with losses that turn into wash sells. | M59: =VLOOKUP(A59,Model!C$2:J$93,2,FALSE)=C59 -> TRUE | O59: =VLOOKUP(A59,Model!C$2:J$93,3,FALSE)=H59 -> FALSE | P59: =VLOOKUP(A59,Model!C$2:J$93,3,FALSE) -> MAXIT Source: TAXLOT_DTL_OPN.DISALWD_WASHSALE_AMT RJT Source: TAX_LOT_OPN_MSTR.NML_CCY_WASH_SALE_AMT | Q59: =VLOOKUP(A59,Model!C$2:J$93,8,FALSE) -> 58 | R59: =VLOOKUP(C59,Table!A$2:F$98,1,FALSE)=C59 -> TRUE | S59: =VLOOKUP(SUBSTITUTE(A59," ","_"),View!A$2:I$106,1,FALSE) -> SYSTEM_BASE_CURRENCY_DISALLOWED_WASH_SALE_AMOUNT | T59: TAXLOT_STG_OWNER | U59: OPN_TAX_LOTS_NONBKR_TGT | V59: SBC_WASH_SALE_AMT | W59: NUMBER(22,6) | X59: Yes
A60: System Base Currency Adjusted Cost | C60: SBC_ADJ_COST | D60: NUMBER(22,6) | E60: Yes | F60: NUMERIC(22,6) | G60: Yes | H60: Adjusted cost for the Lot | M60: =VLOOKUP(A60,Model!C$2:J$93,2,FALSE)=C60 -> TRUE | O60: =VLOOKUP(A60,Model!C$2:J$93,3,FALSE)=H60 -> FALSE | P60: =VLOOKUP(A60,Model!C$2:J$93,3,FALSE) -> Adjusted cost for the Lot MAXIT source: TAXLOT_DTL_OPN.ADJ_COST RJT Source: TAX_LOT_OPN_ASOF NML_CCY_ASOF_ADJ_COST_AMT | Q60: =VLOOKUP(A60,Model!C$2:J$93,8,FALSE) -> 59 | R60: =VLOOKUP(C60,Table!A$2:F$98,1,FALSE)=C60 -> TRUE | S60: =VLOOKUP(SUBSTITUTE(A60," ","_"),View!A$2:I$106,1,FALSE) -> SYSTEM_BASE_CURRENCY_ADJUSTED_COST | T60: TAXLOT_STG_OWNER | U60: OPN_TAX_LOTS_NONBKR_TGT | V60: SBC_ASOF_ADJ_COST_AMT | W60: NUMBER(22,6) | X60: Yes | Y60: ADJ_COST, case when (CCY_CODE ='USD' or (EXG_RATE is NULL OR EXG_RATE = 0)) THEN ADJ_COST ELSE ADJ_COST * EXG_RATE END SBC_ADJ_COST
A61: System Base Currency Fair Market Value | C61: SBC_FAIR_MKT_VAL | D61: NUMBER(22,6) | E61: Yes | F61: NUMERIC(22,6) | G61: Yes | H61: fair market value of the tax lot at the point of gifting or inheritance per system base currency | M61: =VLOOKUP(A61,Model!C$2:J$93,2,FALSE)=C61 -> TRUE | O61: =VLOOKUP(A61,Model!C$2:J$93,3,FALSE)=H61 -> FALSE | P61: =VLOOKUP(A61,Model!C$2:J$93,3,FALSE) -> MAXIT Source: TAXLOT_DTL_OPN.FMV For MAXIT (Brokerage) Fair market value of the tax lot at the point of gifting or inheritance Source: FMV For gifted or inherited transactions only. Sourced from: 1) account to account RAD Activity receive record sent to Maxit from RJ 2) CBRS record received from contra firm 3) manual entry by business | Q61: =VLOOKUP(A61,Model!C$2:J$93,8,FALSE) -> 60 | R61: =VLOOKUP(C61,Table!A$2:F$98,1,FALSE)=C61 -> TRUE | S61: =VLOOKUP(SUBSTITUTE(A61," ","_"),View!A$2:I$106,1,FALSE) -> SYSTEM_BASE_CURRENCY_FAIR_MARKET_VALUE | T61: TAXLOT_STG_OWNER | U61: OPN_TAX_LOTS_NONBKR_TGT | V61: SBC_ASOF_FAIR_MKT_VAL_AMT | W61: NUMBER(22,6) | X61: Yes | Y61: FMV FAIR_MKT_VAL_OF_GIFT_OR_INHTN, case when (CCY_CODE ='USD' or (EXG_RATE is NULL OR EXG_RATE = 0)) THEN FMV ELSE FMV * EXG_RATE END SBC_FAIR_MKT_VAL
A62: System Base Currency Open Price Factor | C62: SBC_OPN_PRC_FCTR | D62: NUMBER(22,6) | E62: Yes | F62: NUMERIC(22,6) | G62: Yes | H62: Price_factor of opening transaction Used for factored bonds | M62: =VLOOKUP(A62,Model!C$2:J$93,2,FALSE)=C62 -> TRUE | O62: =VLOOKUP(A62,Model!C$2:J$93,3,FALSE)=H62 -> FALSE | P62: =VLOOKUP(A62,Model!C$2:J$93,3,FALSE) -> Price_factor of opening transaction Used for factored bonds MAXIT Source: TAXLOT_DTL_OPN.OPN_FCTR RJT Source: TAX_LOT_OPN_MSTR.NML_CCY_OPN_PRC_FCTR | Q62: =VLOOKUP(A62,Model!C$2:J$93,8,FALSE) -> 61 | R62: =VLOOKUP(C62,Table!A$2:F$98,1,FALSE)=C62 -> TRUE | S62: =VLOOKUP(SUBSTITUTE(A62," ","_"),View!A$2:I$106,1,FALSE) -> SYSTEM_BASE_CURRENCY_OPEN_PRICE_FACTOR | T62: TAXLOT_STG_OWNER | U62: OPN_TAX_LOTS_NONBKR_TGT | V62: SBC_OPN_PRC_FCTR | W62: NUMBER(22,6) | X62: Yes | Y62: OPN_FCTR OPN_PRC_FCTR, case when (CCY_CODE ='USD' or (EXG_RATE is NULL OR EXG_RATE = 0)) THEN OPN_FCTR ELSE OPN_FCTR * EXG_RATE END SBC_OPN_PRC_FCTR
A63: System Base Currency Cost Amount | C63: SBC_COST_AMT | D63: NUMBER(22,6) | E63: Yes | F63: NUMERIC(22,6) | G63: Yes | H63: Original total purchase cost of the instrument Buy, the net amount is shown. Sell, cost sold for a sell is displayed. Note: This field cannot be used currently as it is not prorated or adjusted for changes/actions/partial sells where a change in quantity is made. | M63: =VLOOKUP(A63,Model!C$2:J$93,2,FALSE)=C63 -> TRUE | O63: =VLOOKUP(A63,Model!C$2:J$93,3,FALSE)=H63 -> FALSE | P63: =VLOOKUP(A63,Model!C$2:J$93,3,FALSE) -> Original total purchase cost of the instrument Buy, the net amount is shown. Sell, cost sold for a sell is displayed. Note: This field cannot be used currently as it is not prorated or adjusted for changes/actions/partial sells where a change in quantity is made. MAXIT Source: TAXLOT_DTL_OPN.ORIG_COST RJT Source:TAX_LOT_OPN_ASOF.NML_ASOF_CRN_COST_AMT | Q63: =VLOOKUP(A63,Model!C$2:J$93,8,FALSE) -> 62 | R63: =VLOOKUP(C63,Table!A$2:F$98,1,FALSE)=C63 -> TRUE | S63: =VLOOKUP(SUBSTITUTE(A63," ","_"),View!A$2:I$106,1,FALSE) -> SYSTEM_BASE_CURRENCY_COST_AMOUNT | T63: TAXLOT_STG_OWNER | U63: OPN_TAX_LOTS_NONBKR_TGT | V63: SBC_OPN_COST_AMT | W63: NUMBER(22,6) | X63: Yes | Y63: ORIG_COST COST_AMT, case when (CCY_CODE ='USD' or (EXG_RATE is NULL OR EXG_RATE = 0)) THEN ORIG_COST ELSE ORIG_COST * EXG_RATE END SBC_COST_AMT
A64: System Base Currency Original Price | C64: SBC_ORIG_PRC | D64: NUMBER(30,8) | E64: Yes | F64: NUMERIC(30,8) | G64: Yes | H64: Per share price of the opening tax lot. big_prc of the Buy/open short. Will be populated for a sell with opening price. Note: This field cannot be used currently as it is not prorated or adjusted for changes/actions/partial sells where a change in quantity is made. | M64: =VLOOKUP(A64,Model!C$2:J$93,2,FALSE)=C64 -> TRUE | O64: =VLOOKUP(A64,Model!C$2:J$93,3,FALSE)=H64 -> FALSE | P64: =VLOOKUP(A64,Model!C$2:J$93,3,FALSE) -> Per share price of the opening tax lot. big_prc of the Buy/open short. Will be populated for a sell with opening price. Note: This field cannot be used currently as it is not prorated or adjusted for changes/actions/partial sells where a change in quantity is made. MAXIT Source: TAXLOT_DTL_OPN.ORIG_PRC RJT Source: TAX_LOT_OPN_MSTR.NML_CCY_ORIG_PRC | Q64: =VLOOKUP(A64,Model!C$2:J$93,8,FALSE) -> 63 | R64: =VLOOKUP(C64,Table!A$2:F$98,1,FALSE)=C64 -> TRUE | S64: =VLOOKUP(SUBSTITUTE(A64," ","_"),View!A$2:I$106,1,FALSE) -> SYSTEM_BASE_CURRENCY_ORIGINAL_PRICE | T64: TAXLOT_STG_OWNER | U64: OPN_TAX_LOTS_NONBKR_TGT | V64: SBC_ORIG_PRC | W64: NUMBER(30,8) | X64: Yes | Y64: ORIG_PRC, case when (CCY_CODE ='USD' or (EXG_RATE is NULL OR EXG_RATE = 0)) THEN ORIG_PRC ELSE ORIG_PRC * EXG_RATE END SBC_ORIG_PRC
A65: System Base Currency Original Proceed | C65: SBC_ORIG_PROCD | D65: NUMBER(22,6) | E65: Yes | F65: NUMERIC(22,6) | G65: Yes | H65: Net_amount of asgn sell before adding premium. Note: This field cannot be used currently as it is not prorated or adjusted for changes/actions/partial sells where a change in quantity is made. | M65: =VLOOKUP(A65,Model!C$2:J$93,2,FALSE)=C65 -> TRUE | O65: =VLOOKUP(A65,Model!C$2:J$93,3,FALSE)=H65 -> FALSE | P65: =VLOOKUP(A65,Model!C$2:J$93,3,FALSE) -> Net_amount of asgn sell before adding premium. Note: This field cannot be used currently as it is not prorated or adjusted for changes/actions/partial sells where a change in quantity is made. MAXIT Source: TAXLOT_DTL_OPN.ORIG_PROCD RJT Source: TAX_LOT_OPN_MSTR.NML_CCY_ORIG_PROCD_AMT | Q65: =VLOOKUP(A65,Model!C$2:J$93,8,FALSE) -> 64 | R65: =VLOOKUP(C65,Table!A$2:F$98,1,FALSE)=C65 -> TRUE | S65: =VLOOKUP(SUBSTITUTE(A65," ","_"),View!A$2:I$106,1,FALSE) -> SYSTEM_BASE_CURRENCY_ORIGINAL_PROCEED | T65: TAXLOT_STG_OWNER | U65: OPN_TAX_LOTS_NONBKR_TGT | V65: SBC_ORIG_PROCD_AMT | W65: NUMBER(22,6) | X65: Yes | Y65: ORIG_PROCD, case when (CCY_CODE ='USD' or (EXG_RATE is NULL OR EXG_RATE = 0)) THEN ORIG_PROCD ELSE ORIG_PROCD * EXG_RATE END SBC_ORIG_PROCD
A66: Source System Id | C66: SRC_STM_ID | D66: NUMBER(38,0) | E66: Yes | F66: NUMERIC(38,0) | G66: Yes | H66: Identifer of the Source System | M66: =VLOOKUP(A66,Model!C$2:J$93,2,FALSE)=C66 -> TRUE | O66: =VLOOKUP(A66,Model!C$2:J$93,3,FALSE)=H66 -> FALSE | P66: =VLOOKUP(A66,Model!C$2:J$93,3,FALSE) -> MAXIT: Hardcode ??? We need to setup a source system RJT Source: TAX_LOT_OPN_MSTR.SRC_STM_ID | Q66: =VLOOKUP(A66,Model!C$2:J$93,8,FALSE) -> 66 | R66: =VLOOKUP(C66,Table!A$2:F$98,1,FALSE)=C66 -> TRUE | S66: =VLOOKUP(SUBSTITUTE(A66," ","_"),View!A$2:I$106,1,FALSE) -> SOURCE_SYSTEM_ID | T66: TAXLOT_STG_OWNER | U66: OPN_TAX_LOTS_NONBKR_TGT | V66: SRC_STM_ID | W66: NUMBER(38,0) | X66: Yes
A67: Source System Name | C67: SRC_STM_NM | D67: VARCHAR2(60) | E67: Yes | F67: Character Varying(60) | G67: Yes | H67: Name of the source system | M67: =VLOOKUP(A67,Model!C$2:J$93,2,FALSE)=C67 -> TRUE | O67: =VLOOKUP(A67,Model!C$2:J$93,3,FALSE)=H67 -> FALSE | P67: =VLOOKUP(A67,Model!C$2:J$93,3,FALSE) -> Name of the source system e.g., SIS - Securities Industry Software, Raymond James, Raymond James Bank, Shadow Suite MAXIT: Hardcode ??? We need to setup a source system RJT Source: TAX_LOT_OPN_MSTR.SRC_STM_ID | Q67: =VLOOKUP(A67,Model!C$2:J$93,8,FALSE) -> 67 | R67: =VLOOKUP(C67,Table!A$2:F$98,1,FALSE)=C67 -> TRUE | S67: =VLOOKUP(SUBSTITUTE(A67," ","_"),View!A$2:I$106,1,FALSE) -> SOURCE_SYSTEM_NAME | T67: COMMON_OWNER | U67: SRC_STM_DIM | V67: SRC_STM_NM | W67: VARCHAR2(60) | X67: Yes | Y67: Use SRC_STM_ID to get name
A68: Accounting Type Id | C68: ACG_TP_ID | D68: NUMBER(38,0) | E68: Yes | F68: NUMERIC(38,0) | G68: Yes | H68: Numeric identifier of the accounting type ID (e.g., 1006, 1001) Lookup using Accounting type Code( RJT TAX_LOT_OPN_MSTR.ACG_TP_CODE) | M68: =VLOOKUP(A68,Model!C$2:J$93,2,FALSE)=C68 -> TRUE | O68: =VLOOKUP(A68,Model!C$2:J$93,3,FALSE)=H68 -> FALSE | P68: =VLOOKUP(A68,Model!C$2:J$93,3,FALSE) -> Numeric identifier of the accounting type ID (e.g., 1006, 1001) Lookup using Accounting type Code (MAXIT TAXLOT_DTL_OPN.AC_TP, RJT TAX_LOT_OPN_MSTR.ACG_TP_CODE) | Q68: =VLOOKUP(A68,Model!C$2:J$93,8,FALSE) -> 68 | R68: =VLOOKUP(C68,Table!A$2:F$98,1,FALSE)=C68 -> TRUE | S68: =VLOOKUP(SUBSTITUTE(A68," ","_"),View!A$2:I$106,1,FALSE) -> ACCOUNTING_TYPE_ID | T68: COMMON_OWNER | U68: ACG_TP_DIM | V68: ACG_TP_ID | W68: NUMBER(38,0) | X68: Yes | Y68: Use TAX_LOT_OPN_MSTR.ACG_TP_CODE to get ACG_TP_ID
A69: Tax Lot Type | C69: TAX_LOT_TP | D69: VARCHAR2(500) | E69: Yes | F69: Character Varying(500) | G69: Yes | H69: logic: 1. For inherited tax lots, it is set to Inherited 1.1. For Brokerage accounts, this is when the ACAT Type is null and Original Transaction Type is INH from the tax lot detail open table or ACAT Type is INH from the tax lot detail open table 1.2. For RJ Trust accounts, this is when the Tax Lot Transaction Type Identifier is 2846 from the tax lot open master table 2. For gifted or gifted then inherited tax lots, it is set to Gift 2.1 For Brokerage accounts, this is when the ACAT Type is null and Original Transaction Type is GFT from the tax lot detail open table or ACAT Type is GFT or ITG from the tax lot detail open table 2.2 For RJ Trust accounts, this is when the Tax Lot Transaction Type Identifier is 2851 from the tax lot open master table 3. For reinvested tax lots, it is set to Reinvestment 3.1. For Brokerage accounts, this is when the ACAT Type is not GFT, INH or ITG and the Reinvest Flag is Y from the tax lot detail open table 3.2. For RJ Trust accounts, this is when the Tax Lot Transaction Type Identifier is not 2846 or 2851 and the Reinvest Flag is Y from the tax lot open master table 4. For all other tax lots 4.1 For Brokerage accounts, it is the High Level Definition from the record type table where 4.1.1. Open Close Indicator from record type table is O 4.1.2. Realized Closing Flag is N 4.1.3. Opening Transaction Event Id from the tax lot detail open table matches the Transaction Event Id from record type table 4.1.4. Otherwise, if match is not found, then set to null 4.2 For RJ Trust accounts, it is the Classification Value Name from the classification value table where 4.2.1 Tax Lot Transaction Type Identifier from the tax lot open master table matches the Classification Value Identifier from the classification table 4.2.2Classification Source Identifier from the classification table is 84 4.3 Otherwise, if match is not found, then set to null | M69: =VLOOKUP(A69,Model!C$2:J$93,2,FALSE)=C69 -> TRUE | O69: =VLOOKUP(A69,Model!C$2:J$93,3,FALSE)=H69 -> FALSE | P69: =VLOOKUP(A69,Model!C$2:J$93,3,FALSE) -> logic: 1. For inherited tax lots, it is set to Inherited 1.1. For Brokerage accounts, this is when the ACAT Type is null and Original Transaction Type is INH from the tax lot detail open table or ACAT Type is INH from the tax lot detail open table 1.2. For RJ Trust accounts, this is when the Tax Lot Transaction Type Identifier is 2846 from the tax lot open master table 2. For gifted or gifted then inherited tax lots, it is set to Gift 2.1 For Brokerage accounts, this is when the ACAT Type is null and Original Transaction Type is GFT from the tax lot detail open table or ACAT Type is GFT or ITG from the tax lot detail open table 2.2 For RJ Trust accounts, this is when the Tax Lot Transaction Type Identifier is 2851 from the tax lot open master table 3. For reinvested tax lots, it is set to Reinvestment 3.1. For Brokerage accounts, this is when the ACAT Type is not GFT, INH or ITG and the Reinvest Flag is Y from the tax lot detail open table 3.2. For RJ Trust accounts, this is when the Tax Lot Transaction Type Identifier is not 2846 or 2851 and the Reinvest Flag is Y from the tax lot open master table 4. For all other tax lots 4.1 For Brokerage accounts, it is the High Level Definition from the record type table where 4.1.1. Open Close Indicator from record type table is O 4.1.2. Realized Closing Flag is N 4.1.3. Opening Transaction Event Id from the tax lot detail open table matches the Transaction Event Id from record type table 4.1.4. Otherwise, if match is not found, then set to null 4.2 For RJ Trust accounts, it is the Classification Value Name from the classification value table where 4.2.1 Tax Lot Transaction Type Identifier from the tax lot open master table matches the Classification Value Identifier from the classification table 4.2.2Classification Source Identifier from the classification table is 84 4.3 Otherwise, if match is not found, then set to null | Q69: =VLOOKUP(A69,Model!C$2:J$93,8,FALSE) -> 74 | R69: =VLOOKUP(C69,Table!A$2:F$98,1,FALSE)=C69 -> TRUE | S69: =VLOOKUP(SUBSTITUTE(A69," ","_"),View!A$2:I$106,1,FALSE) -> TAX_LOT_TYPE | T69: CCAL_REPL_OWNER | U69: CL_VAL | V69: CL_VAL_NM | X69: Yes | Y69: Use TAX_LOT_TXN_TP_ID as CL_Val_id and get CL_VAL_NM where CL_SCM_ID = 84
A70: Cost Basis Legislation Coverage Flag | C70: COST_BSS_LEGS_CVR_F | D70: VARCHAR2(1) | E70: Yes | F70: Character Varying(1) | G70: Yes | H70: For RJ Trust accounts if the Covered Flag from the tax lot open master table is C, then set to Y Otherwise, set to N | M70: =VLOOKUP(A70,Model!C$2:J$93,2,FALSE)=C70 -> TRUE | O70: =VLOOKUP(A70,Model!C$2:J$93,3,FALSE)=H70 -> FALSE | P70: =VLOOKUP(A70,Model!C$2:J$93,3,FALSE) -> For Brokerage if the covered uncovered from tax lot detail open table is C, then set to Y Otherwise, set to N For RJ Trust accounts if the Covered Flag from the tax lot open master table is C, then set to Y Otherwise, set to N | Q70: =VLOOKUP(A70,Model!C$2:J$93,8,FALSE) -> 75 | R70: =VLOOKUP(C70,Table!A$2:F$98,1,FALSE)=C70 -> TRUE | S70: =VLOOKUP(SUBSTITUTE(A70," ","_"),View!A$2:I$106,1,FALSE) -> COST_BASIS_LEGISLATION_COVERAGE_FLAG | T70: TAXLOT_STG_OWNER | U70: OPN_TAX_LOTS_NONBKR_TGT | V70: CVRD_UNCVRD | W70: VARCHAR2(1) | X70: Yes | Y70: (case when TAXLOT_DTL_OPN.CVRD_UNCVRD = 'C' then 'Y' else 'N' end) AS COST_BSS_LEGS_CVR_F
A71: Missing Invest Cost Flag | C71: MISS_IVS_COST_F | D71: VARCHAR2(1) | E71: Yes | F71: Character Varying(1) | G71: Yes | H71: For RJ Trust accounts If the reinvest flag from tax lot open master is not equal to Y If the Missing Cost Flag from the tax lot open master table is Y, then set to Y If the Null Basis Flag from the tax lot open master table is Y, then set to Y Otherwise, set to N | M71: =VLOOKUP(A71,Model!C$2:J$93,2,FALSE)=C71 -> TRUE | O71: =VLOOKUP(A71,Model!C$2:J$93,3,FALSE)=H71 -> FALSE | P71: =VLOOKUP(A71,Model!C$2:J$93,3,FALSE) -> For Brokerage accounts_x000D_ If the reinvest flag from tax lot detail open is not equal to Y_x000D_ If the missing cost flag from tax lot detail open is Y, then set to Y_x000D_ If the missing average cost flag (null flag) from tax lot detail open is Y, then set to Y_x000D_ Otherwise, set to N_x000D_ _x000D_ For RJ Trust accounts_x000D_ If the reinvest flag from tax lot open master is not equal to Y_x000D_ If the Missing Cost Flag from the tax lot open master table is Y, then set to Y_x000D_ If the Null Basis Flag from the tax lot open master table is Y, then set to Y_x000D_ ?Otherwise, set to N_x000D_ _x000D_ | Q71: =VLOOKUP(A71,Model!C$2:J$93,8,FALSE) -> 77 | R71: =VLOOKUP(C71,Table!A$2:F$98,1,FALSE)=C71 -> TRUE | S71: =VLOOKUP(SUBSTITUTE(A71," ","_"),View!A$2:I$106,1,FALSE) -> MISSING_INVEST_COST_FLAG | W71: VARCHAR2(1) | X71: Yes | Y71: CASE WHEN (TAX_LOT_OPN_MSTR.RVST_F<>'Y' AND (TAX_LOT_OPN_MSTR.MISS_COST_F = 'Y' OR TAX_LOT_OPN_MSTR.null_bss_f = 'Y')) THEN 'Y' ELSE 'N' END
A72: Session Number | C72: SESN_NUM | D72: NUMBER(38,0) | E72: Yes | F72: NUMERIC(38,0) | G72: Yes | H72: ODI Session Number for last update | M72: =VLOOKUP(A72,Model!C$2:J$93,2,FALSE)=C72 -> TRUE | O72: =VLOOKUP(A72,Model!C$2:J$93,3,FALSE)=H72 -> FALSE | P72: =VLOOKUP(A72,Model!C$2:J$93,3,FALSE) -> 0 | Q72: =VLOOKUP(A72,Model!C$2:J$93,8,FALSE) -> 65 | R72: =VLOOKUP(C72,Table!A$2:F$98,1,FALSE)=C72 -> TRUE | S72: =VLOOKUP(SUBSTITUTE(A72," ","_"),View!A$2:I$106,1,FALSE) -> #N/A | X72: Yes
A73: Create Datetime | C73: CRT_DTM | D73: TIMESTAMP(6) | E73: No | F73: TIMESTAMP(6) | G73: No | H73: The exact date when a Open Tax Lot Fact was first created. | M73: =VLOOKUP(A73,Model!C$2:J$93,2,FALSE)=C73 -> TRUE | O73: =VLOOKUP(A73,Model!C$2:J$93,3,FALSE)=H73 -> FALSE | P73: =VLOOKUP(A73,Model!C$2:J$93,3,FALSE) -> 0 | Q73: =VLOOKUP(A73,Model!C$2:J$93,8,FALSE) -> 69 | R73: =VLOOKUP(C73,Table!A$2:F$98,1,FALSE)=C73 -> TRUE | S73: =VLOOKUP(SUBSTITUTE(A73," ","_"),View!A$2:I$106,1,FALSE) -> CREATE_DATETIME | X73: No
A74: Create User Name | C74: CRT_USR_NM | D74: VARCHAR2(256) | E74: No | F74: Character Varying(256) | G74: No | H74: The name that represents the user who created an occurrence of a/an Position Open Tax Lots. | M74: =VLOOKUP(A74,Model!C$2:J$93,2,FALSE)=C74 -> TRUE | O74: =VLOOKUP(A74,Model!C$2:J$93,3,FALSE)=H74 -> FALSE | P74: =VLOOKUP(A74,Model!C$2:J$93,3,FALSE) -> The name that represents the user who created an occurrence of a/an Open Tax Lots Fact. | Q74: =VLOOKUP(A74,Model!C$2:J$93,8,FALSE) -> 70 | R74: =VLOOKUP(C74,Table!A$2:F$98,1,FALSE)=C74 -> TRUE | S74: =VLOOKUP(SUBSTITUTE(A74," ","_"),View!A$2:I$106,1,FALSE) -> CREATE_USER_NAME | X74: No
A75: Last Update Datetime | C75: LAST_UDT_DTM | D75: TIMESTAMP(6) | E75: No | F75: TIMESTAMP(6) | G75: No | H75: The time that represents the user or application who inserted, updated, or deleted each occurrence of Position Open Tax Lots . | M75: =VLOOKUP(A75,Model!C$2:J$93,2,FALSE)=C75 -> TRUE | O75: =VLOOKUP(A75,Model!C$2:J$93,3,FALSE)=H75 -> FALSE | P75: =VLOOKUP(A75,Model!C$2:J$93,3,FALSE) -> 0 | Q75: =VLOOKUP(A75,Model!C$2:J$93,8,FALSE) -> 71 | R75: =VLOOKUP(C75,Table!A$2:F$98,1,FALSE)=C75 -> TRUE | S75: =VLOOKUP(SUBSTITUTE(A75," ","_"),View!A$2:I$106,1,FALSE) -> LAST_UPDATE_DATETIME | X75: No
A76: Last Update User Name | C76: LAST_UDT_USR_NM | D76: VARCHAR2(256) | E76: No | F76: Character Varying(256) | G76: No | H76: The name that represents the user or application who inserted, updated, or deleted each occurrence of Position Open Tax Lots . | M76: =VLOOKUP(A76,Model!C$2:J$93,2,FALSE)=C76 -> TRUE | O76: =VLOOKUP(A76,Model!C$2:J$93,3,FALSE)=H76 -> FALSE | P76: =VLOOKUP(A76,Model!C$2:J$93,3,FALSE) -> The name that represents the user or application who inserted, updated, or deleted each occurrence of Open Tax Lots Fact. | Q76: =VLOOKUP(A76,Model!C$2:J$93,8,FALSE) -> 72 | R76: =VLOOKUP(C76,Table!A$2:F$98,1,FALSE)=C76 -> TRUE | S76: =VLOOKUP(SUBSTITUTE(A76," ","_"),View!A$2:I$106,1,FALSE) -> LAST_UPDATE_USER_NAME | X76: No

Sheet View
A1: COLUMN_NAME | B1: DATA_TYPE | C1: NULLABLE | D1: DATA_DEFAULT | E1: COLUMN_ID | F1: COMMENTS | G1: INSERTABLE | H1: UPDATABLE | I1: DELETABLE
A2: ACAT_TYPE | B2: VARCHAR2(500) | C2: Yes | E2: 15 | G2: YES | H2: YES | I2: YES
A3: ACAT_TYPE_CODE | B3: VARCHAR2(40) | C3: Yes | E3: 16 | G3: YES | H3: YES | I3: YES
A4: ACCOUNTING_TYPE_CODE | B4: VARCHAR2(1) | C4: Yes | E4: 6 | G4: YES | H4: YES | I4: YES
A5: ACCOUNTING_TYPE_DIMENSION_ID | B5: NUMBER(38) | C5: No | E5: 13 | G5: YES | H5: YES | I5: YES
A6: ACCOUNTING_TYPE_ID | B6: NUMBER(38) | C6: Yes | E6: 67 | G6: YES | H6: YES | I6: YES
A7: ACCOUNTING_TYPE_NAME | B7: VARCHAR2(500) | C7: Yes | E7: 14 | G7: YES | H7: YES | I7: YES
A8: ACQUIRED_DATE | B8: DATE | C8: Yes | E8: 17 | G8: YES | H8: YES | I8: YES
A9: ACQUIRED_DATE_DIMENSION_ID | B9: NUMBER(38) | C9: No | E9: 72 | G9: YES | H9: YES | I9: YES
A10: ADJUSTED_COST | B10: NUMBER(22,6) | C10: Yes | E10: 18 | G10: YES | H10: YES | I10: YES
A11: ADJUSTED_COST_NOT_ACCURATE_FLAG | B11: VARCHAR2(1) | C11: Yes | E11: 34 | G11: YES | H11: YES | I11: YES
A12: ARRANGEMENT_ID | B12: NUMBER | C12: Yes | E12: 3 | G12: YES | H12: YES | I12: YES
A13: BUY_TRADE_NUMBER | B13: VARCHAR2(80) | C13: Yes | E13: 20 | G13: YES | H13: YES | I13: YES
... A82: ZERO_COST_BASIS_FLAG | B82: VARCHAR2(2) | C82: Yes | E82: 54 | G82: YES | H82: YES | I82: YES

Sheet Grain Columns

Sheet ETL Notes

Sheet Additional View
A1: 1. View Name -
A2: 3. View Schema Name - SSDS_DAL_OWNER
A3: 5. Table Functional Description -
A4: 6. Filter Criteria - NA
A5: Logic if necessary:

Sheet Model
A1: Entity Name | B1: Table Name | C1: Attribute Name | D1: Column Name | E1: Attribute/Column Definition | F1: Domain | G1: Column Datatype | H1: Column Null Option
A2: Open Tax Lots Fact | B2: OPN_TAX_LOTS_FACT | C2: Acat Type | D2: ACAT_TP | E2: MAXIT Source: = TAXLOT_DTL_OPN.ACATTYPE RJT Source: None Type of Transfer indicated by the external source when transferred using ACAT Values GFT = Gift INH = Inherited ITG = Inherited Than Gifted NTT = NonTaxable to Taxable DRIP = A Direct Registration System (DRS)/Direct Reinvestment Plan NULL = none various other values are available as well | F2: Name_desc | G2: VARCHAR2(500) | H2: NULL | J2: 17
A3: Open Tax Lots Fact | B3: OPN_TAX_LOTS_FACT | C3: Acat Type Code | D3: ACAT_TP_CD | E3: MAXIT Source: = TAXLOT_DTL_OPN.ACATTYPE RJT Source: None Type of Transfer Code indicated by the external source when transferred using ACAT Values GFT = Gift INH = Inherited ITG = Inherited Than Gifted NTT = NonTaxable to Taxable DRIP = A Direct Registration System (DRS)/Direct Reinvestment Plan NULL = none various other values are available as well | F3: Code | G3: VARCHAR2(40) | H3: NULL | J3: 18
A4: Open Tax Lots Fact | B4: OPN_TAX_LOTS_FACT | C4: Accounting Type Code | D4: ACG_TP_CD | E4: MAXIT Source: TAXLOT_DTL_OPN.AC_TP RJT Source: TAX_LOT_OPN_MSTR.ACG_TP_CODE Accounting type code from SIS (e.g., 1,2,6). 1= Cash Account 2= Margin Account 3= Special lot 2019 5= Special lot 2013 6= Short margin Account | F4: Code_01 | G4: VARCHAR2(1) | H4: NULL | J4: 8
A5: Open Tax Lots Fact | B5: OPN_TAX_LOTS_FACT | C5: Accounting Type Dimension Id | D5: ACG_TP_DIM_ID | E5: MAXIT Source: TAXLOT_DTL_OPN.AC_TP RJT Source: TAX_LOT_OPN_MSTR.ACG_TP_CODE Lookup on Accounting Type Dimension | F5: NINI | G5: NUMBER(38,0) | H5: NULL | J5: 15
A6: Open Tax Lots Fact | B6: OPN_TAX_LOTS_FACT | C6: Accounting Type Id | D6: ACG_TP_ID | E6: Numeric identifier of the accounting type ID (e.g., 1006, 1001) Lookup using Accounting type Code (MAXIT TAXLOT_DTL_OPN.AC_TP, RJT TAX_LOT_OPN_MSTR.ACG_TP_CODE) | F6: NINI | G6: NUMBER(38,0) | H6: NULL | J6: 68
A7: Open Tax Lots Fact | B7: OPN_TAX_LOTS_FACT | C7: Accounting Type Name | D7: ACG_TP_NM | E7: MAXIT Source: TAXLOT_DTL_OPN.AC_TP RJT Source: TAX_LOT_OPN_MSTR.ACG_TP_CODE Lookup on Accounting Type Dimension Accounting type name (e.g., cash account,margin account) | F7: Name_desc | G7: VARCHAR2(500) | H7: NULL | J7: 16
A8: Open Tax Lots Fact | B8: OPN_TAX_LOTS_FACT | C8: Acquired Date | D8: ACQ_DT | E8: Date on which the lot was acquired_x000D_ MAXIT source: TAXLOT_DTL_OPN.ACQ_DT_x000D_ RJT Source:TAX_LOT_OPN_MSTR.TD_x000D_ _x000D_ | F8: Date | G8: DATE | H8: NULL | J8: 19
A9: Open Tax Lots Fact | B9: OPN_TAX_LOTS_FACT | C9: Acquired Date Dimension Id | D9: ACQ_DT_DIM_ID | E9: Synthetic Key identifying a single date in the DATE Dimension | F9: NINI | G9: NUMBER(38,0) | H9: NOT NULL | J9: 80
A10: Open Tax Lots Fact | B10: OPN_TAX_LOTS_FACT | C10: Adjusted Cost | D10: ADJ_COST | E10: Adjusted cost for the Lot MAXIT source: TAXLOT_DTL_OPN.ADJ_COST RJT Source: TAX_LOT_OPN_ASOF NML_CCY_ASOF_ADJ_COST_AMT | F10: a | G10: NUMBER(22,6) | H10: NULL | J10: 20
A11: Open Tax Lots Fact | B11: OPN_TAX_LOTS_FACT | C11: Adjusted cost Not Accurate Flag | D11: ADJ_COST_NOT_ACRT_F | E11: MAXIT Source: TAXLOT_DTL_OPN.NULL_F RJT Source: TAX_LOT_OPN_MSTR.NULL_BSS_F Indcates that Adjusted Cost is not accurate due to missing cost on atleast one sublot Source:NULL_F Y = YES ? At least one of the associated average cost records is missing average cost N = NO ? None of the associated average cost records are missing average cost | F11: Flag | G11: VARCHAR2(1) | H11: NULL | J11: 36
A12: Open Tax Lots Fact | B12: OPN_TAX_LOTS_FACT | C12: Arrangement Dimension Id | D12: AR_DIM_ID | E12: Arrangement Id for the account MAXIT Source: TAX_LOT_DTL_OPN/CLS.AR_ID RJT Source:TAX_LOT_OPN_MSTR.AR_ID Lookup on AR_DIM using EFF_DT | F12: NINI | G12: NUMBER(38,0) | H12: NOT NULL | J12: 7
A13: Open Tax Lots Fact | B13: OPN_TAX_LOTS_FACT | C13: Arrangement Id | D13: AR_ID | E13: Arrangement Id for the account MAXIT Source:TAX_LOT_DTL_OPN/CLS.AR_ID RJT Source:TAX_LOT_OPN_MSTR.AR_ID | F13: NINI | G13: NUMBER(9,0) | H13: NULL | J13: 3
A14: Open Tax Lots Fact | B14: OPN_TAX_LOTS_FACT | C14: Average Adjusted Cost per Unit | D14: AVG_ADJ_COST_PER_UNIT | E14: Calculated. See SRD | F14: a | G14: NUMBER(22,6) | H14: NULL | J14: 79
A15: Open Tax Lots Fact | B15: OPN_TAX_LOTS_FACT | C15: Buy Trade Number | D15: BUY_TRD_NUM | E15: Trade number for the buy when lot was established with a buy transaction MAXIT Source: TAXLOT_DTL_OPN.BUY_TRD_NUM RJT Source: TAX_LOT_OPN_MSTR.TRD_NUM | G15: VARCHAR2(80) | H15: NULL | J15: 22
A16: Open Tax Lots Fact | B16: OPN_TAX_LOTS_FACT | C16: CCAL Product Id | D16: CCAL_PD_ID | E16: Product Id assigned by CCAL MAXIT Source: TAX_LOT_DTL_OPN/CLS.PD_ID RJT Source: TAX_LOT_OPN_MSTR.CCAL_PD_ID | F16: NINI | G16: NUMBER(9,0) | H16: NULL | J16: 5
A17: Open Tax Lots Fact | B17: OPN_TAX_LOTS_FACT | C17: Certificate Number | D17: CTF_NUM | E17: MAXIT Source:TAXLOT_DTL_OPN.CTF_NUM RJT Source: TAX_LOT_OPN_MSTR.TAX_LOT_CTF_NUM | F17: Code | G17: VARCHAR2(40) | H17: NULL | J17: 24
A18: Open Tax Lots Fact | B18: OPN_TAX_LOTS_FACT | C18: Certificate Number Prefix | D18: CTF_NUM_PFX | E18: MAXIT Source:TAXLOT_DTL_OPN.CTF_NUM_PFX RJT Source: TAX_LOT_OPN_MSTR.TAX_LOT_CTF_NUM_PFX | F18: Code | G18: VARCHAR2(40) | H18: NULL | J18: 25
A19: Open Tax Lots Fact | B19: OPN_TAX_LOTS_FACT | C19: CIRD Product Id | D19: CIRD_PD_ID | E19: MAXIT Source: TAX_LOT_DTL_OPN/CLS.PD_ID RJT Source: TAX_LOT_OPN_MSTR.CCAL_PD_ID Lookup on IMT_PD_DIM using CL_PD_ID PD_ID from CIRD - can be used as join key if date context is supplied at query time | F19: NINI | G19: NUMBER(9,0) | H19: NULL | J19: 4
A20: Open Tax Lots Fact | B20: OPN_TAX_LOTS_FACT | C20: Cost Amount | D20: COST_AMT | E20: Original total purchase cost of the instrument Buy, the net amount is shown. Sell, cost sold for a sell is displayed. Note: This field cannot be used currently as it is not prorated or adjusted for changes/actions/partial sells where a change in quantity is made. MAXIT Source: TAXLOT_DTL_OPN.ORIG_COST RJT Source:TAX_LOT_OPN_ASOF.NML_ASOF_CRN_COST_AMT | F20: a | G20: NUMBER(22,6) | H20: NULL | J20: 39
A21: Open Tax Lots Fact | B21: OPN_TAX_LOTS_FACT | C21: Cost Basis Legislation Coverage Code | D21: COST_BSS_LEGS_CVR_CD | E21: Cost Basis Legislation Coverage: ?covered? securities are those impacted by the cost basis legislation (which is dependent on the security type and acquisition date) and subject to the new IRS reporting requirements. U = Uncovered Tax Lot C = Covered Tax Lot MAXIT Source: TAXLOT_DTL_OPN.CVRD_UNCVRD RJT Source: TAX_LOT_OPN_MSTR.CVRD_F | F21: Flag | G21: VARCHAR2(1) | H21: NULL | J21: 26
A22: Open Tax Lots Fact | B22: OPN_TAX_LOTS_FACT | C22: Cost Basis Legislation Coverage Flag | D22: COST_BSS_LEGS_CVR_F | E22: For Brokerage if the covered uncovered from tax lot detail open table is C, then set to Y Otherwise, set to N For RJ Trust accounts if the Covered Flag from the tax lot open master table is C, then set to Y Otherwise, set to N | F22: Flag | G22: VARCHAR2(1) | H22: NULL | J22: 75
A23: Open Tax Lots Fact | B23: OPN_TAX_LOTS_FACT | C23: Cost Basis Shareholder Provided Code | D23: COST_BSS_SHRHLR_PVDD_CD | E23: Cost Basis provided by the client. Y=Yes, N= No other code values 0 (zero) and Null. We do not have documentation on these codes MAXIT Source:TAXLOT_DTL_OPN.BSS_SHP RJT Source: None | F23: Flag | G23: VARCHAR2(1) | H23: NULL | J23: 21
A24: Open Tax Lots Fact | B24: OPN_TAX_LOTS_FACT | C24: Create Datetime | D24: CRT_DTM | F24: Date | G24: TIMESTAMP(6) | H24: NULL | J24: 69
A25: Open Tax Lots Fact | B25: OPN_TAX_LOTS_FACT | C25: Create User Name | D25: CRT_USR_NM | E25: The name that represents the user who created an occurrence of a/an Open Tax Lots Fact. | F25: Create User Name | G25: VARCHAR2(255) | H25: NOT NULL | J25: 70
A26: Open Tax Lots Fact | B26: OPN_TAX_LOTS_FACT | C26: Currency Code | D26: CCY_CD | E26: MAXIT Source: TAXLOT_DTL_OPN.CCY_CODE RJT Source: TAX_LOT_OPN_ASOF.NML_ISO_CCY_CODE | G26: VARCHAR2(7) | H26: NULL | J26: 23
A27: Open Tax Lots Fact | B27: OPN_TAX_LOTS_FACT | C27: Disallowed Wash sale Amount | D27: DISALWD_WASH_SALE_AMT | E27: MAXIT Source: TAXLOT_DTL_OPN.DISALWD_WASHSALE_AMT RJT Source: TAX_LOT_OPN_MSTR.NML_CCY_WASH_SALE_AMT | F27: a | G27: NUMBER(22,6) | H27: NULL | J27: 27
A28: Open Tax Lots Fact | B28: OPN_TAX_LOTS_FACT | C28: Dual Basis Flag | D28: DUAL_BSS_F | E28: Possible values Y = Record is a depreciated dual basis gift N = Record is not a depreciated dual basis gift For Brokerage accounts If the ACAT type is null and the Original Transaction Type is GFT from tax lot detail open And Fair market value from tax lot detail open is greater than zero And Adjusted cost amount from tax lot detail open is greater than zero And Fair market value is less than or equal to adjusted cost amount then Set to Y or If the ACAT Type is GFT or ITG from tax lot detail open and Fair market value from tax lot detail open is greater than zero And Adjusted cost amount from tax lot detail open is greater than zero And Fair market value is less than or equal to adjusted cost amount then Set to Y Otherwise, set to N For RJ Trust accounts If the Tax Lot Transaction Type Identifier is 2851 from the tax lot open master table and the SBC As Of Fair Market Value from the tax lot open as of table is greater than zero and the SBC As Of Adjusted Cost Amount from the tax lot open as of table is greater than zero and the SBC As Of Fair Market Value is less than or equal to the SBC As Of Adjusted Cost Amount then Set to Y Otherwise, set to N | F28: Flag | G28: VARCHAR2(1) | H28: NULL | J28: 76
A29: Open Tax Lots Fact | B29: OPN_TAX_LOTS_FACT | C29: Effective Date | D29: EFf_DT | E29: MAXIT Source: TAXLOT_DTL_OPN.EFF_DT_x000D_ RJT Source: TAX_LOT_OPN_ASOF.EFF_FM_DT_x000D_ _x000D_ | F29: Effective Date | G29: DATE | H29: NOT NULL | J29: 14
A30: Open Tax Lots Fact | B30: OPN_TAX_LOTS_FACT | C30: Effective Date Dimension Id | D30: EFF_DT_DIM_ID | E30: Synthetic Key identifying a single date in the DATE Dimension | F30: NINI | G30: NUMBER(38,0) | H30: NOT NULL | J30: 78
A31: Open Tax Lots Fact | B31: OPN_TAX_LOTS_FACT | C31: End Date | D31: END_DT | E31: MAXIT Source: TAXLOT_DTL_OPN.END_DT RJT Source: TAX_LOT_OPN_ASOF.EFF_TO_DT | G31: DATE | H31: NULL | J31: 13
A32: Open Tax Lots Fact | B32: OPN_TAX_LOTS_FACT | C32: End Date Dimension Id | D32: END_DT_DIM_ID | E32: Synthetic Key identifying a single date in the DATE Dimension | F32: NINI | G32: NUMBER(38,0) | H32: NOT NULL | J32: 81
A33: Open Tax Lots Fact | B33: OPN_TAX_LOTS_FACT | C33: Exchange Rate | D33: EXG_RATE | E33: MAXIT Source: TAXLOT_DTL_OPN.EXG_RATE RJT Source: TAX_LOT_OPN_ASOF.SBC_EXG_RATE | F33: a | G33: NUMBER(22,6) | H33: NULL | J33: 28
A34: Open Tax Lots Fact | B34: OPN_TAX_LOTS_FACT | C34: Fair Market Value Of Gift Or Inheritance | D34: FAIR_MKT_VAL_OF_GIFT_OR_INHTN | E34: MAXIT Source: TAXLOT_DTL_OPN.FMV RJT SOurce: TAX_LOT_OPN_ASOF.NML_CCY_ASOF_FAIR_MKT_VAL_AMT For MAXIT (Brokerage) Fair market value of the tax lot at the point of gifting or inheritance Source: FMV For gifted or inherited transactions only. Sourced from: 1) account to account RAD Activity receive record sent to Maxit from RJ 2) CBRS record received from contra firm 3) manual entry by business | F34: a | G34: NUMBER(22,6) | H34: NULL | J34: 29
A35: Open Tax Lots Fact | B35: OPN_TAX_LOTS_FACT | C35: Gift Date | D35: GIFT_DT | E35: MAXIT Source: TAXLOT_DTL_OPN.GIFT_DT RJT Source: TAX_LOT_OPN_MSTR.GIFT_DT For gifted tax lots this gives date of gift. Source: GIFT_DT | G35: DATE | H35: NULL | J35: 30
A36: Open Tax Lots Fact | B36: OPN_TAX_LOTS_FACT | C36: Gift Date Dimension Id | D36: GIFT_DT_DIM_ID | E36: Synthetic Key identifying a single date in the DATE Dimension | F36: NINI | G36: NUMBER(38,0) | H36: NOT NULL | J36: 82
A37: Open Tax Lots Fact | B37: OPN_TAX_LOTS_FACT | C37: Investment Product Dimension Id | D37: IMT_PD_DIM_ID | E37: MAXIT Source: TAX_LOT_DTL_OPN/CLS.PD_ID RJT Source: TAX_LOT_OPN_MSTR.CCAL_PD_ID Lookup on IMT_PD_DIM using CL_PD_ID | F37: NINI | G37: NUMBER(38,0) | H37: NOT NULL | J37: 6
A38: Open Tax Lots Fact | B38: OPN_TAX_LOTS_FACT | C38: Last Update Datetime | D38: LAST_UDT_DTM | G38: TIMESTAMP(6) | H38: NULL | J38: 71
A39: Open Tax Lots Fact | B39: OPN_TAX_LOTS_FACT | C39: Last Update User Name | D39: LAST_UDT_USR_NM | E39: The name that represents the user or application who inserted, updated, or deleted each occurrence of Open Tax Lots Fact. | F39: Last Update User Name | G39: VARCHAR2(255) | H39: NOT NULL | J39: 72
A40: Open Tax Lots Fact | B40: OPN_TAX_LOTS_FACT | C40: Life to Date Market Discount | D40: LIFE_TO_DTD_MKT_DCN | E40: Life to date market discount amount_x000D_ _x000D_ Total market discount accrued since the purchase of the bond_x000D_ _x000D_ MAXIT Source: TAXLOT_DTL_OPN.LTD_MKT_DISCOUNT | F40: a | G40: NUMBER(22,6) | H40: NULL | I40: Frozen | J40: 34
A41: Open Tax Lots Fact | B41: OPN_TAX_LOTS_FACT | C41: Long Short Position Code | D41: LONG_SHRT_POS_CD | E41: A value that represents the tax lot being a long or short position. Valid Values: L = Long S = Short MAXIT Source: TAXLOT_DTL_OPN.LONG_SHRT_POS rjt sOURCE: TAX_LOT_OPN_MSTR.POS_LONG_SHRT_CODE | F41: Code_01 | G41: VARCHAR2(1) | H41: NULL | J41: 32
A42: Open Tax Lots Fact | B42: OPN_TAX_LOTS_FACT | C42: Loss Not Allowed Flag | D42: LOSS_NOT_ALWD_F | E42: MAXIT Source: TAXLOT_DTL_OPN.LOSS_NOT_ALLOWED RJT Source: None In a cash and stock merger the client may not be allowed to take a loss on the disposition of the old stock, any losses are rolled into the new stock. Merger / Acquisition or Corporate Inversion Transactions. This field is currently used on Closed Tax Lot Tax Reporting at this time. Values: N = No, Loss allowed Y = Yes, No Loss allowed | F42: Flag | G42: VARCHAR2(1) | H42: NULL | J42: 33
A43: Open Tax Lots Fact | B43: OPN_TAX_LOTS_FACT | C43: Missing Cost Basis Flag | D43: MISS_COST_BSS_F | E43: Indicates that Cost basis is not available for this position MAXIT Source: TAXLOT_DTL_OPN.MISS_COST_F RJT Source: TAX_LOT_OPN_MSTR.MISS_COST_F | F43: Flag | G43: VARCHAR2(1) | H43: NULL | J43: 35
A44: Open Tax Lots Fact | B44: OPN_TAX_LOTS_FACT | C44: missing invest cost flag | D44: MISS_IVS_COST_F | E44: For Brokerage accounts_x000D_ If the reinvest flag from tax lot detail open is not equal to Y_x000D_ If the missing cost flag from tax lot detail open is Y, then set to Y_x000D_ If the missing average cost flag (null flag) from tax lot detail open is Y, then set to Y_x000D_ Otherwise, set to N_x000D_ _x000D_ For RJ Trust accounts_x000D_ If the reinvest flag from tax lot open master is not equal to Y_x000D_ If the Missing Cost Flag from the tax lot open master table is Y, then set to Y_x000D_ If the Null Basis Flag from the tax lot open master table is Y, then set to Y_x000D_ ?Otherwise, set to N_x000D_ _x000D_ | F44: Flag | G44: VARCHAR2(1) | H44: NULL | I44: Frozen | J44: 77
A45: Open Tax Lots Fact | B45: OPN_TAX_LOTS_FACT | C45: Open Price Factor | D45: OPN_PRC_FCTR | E45: Price_factor of opening transaction Used for factored bonds MAXIT Source: TAXLOT_DTL_OPN.OPN_FCTR RJT Source: TAX_LOT_OPN_MSTR.NML_CCY_OPN_PRC_FCTR | F45: a | G45: NUMBER(22,6) | H45: NULL | J45: 37
A46: Open Tax Lots Fact | B46: OPN_TAX_LOTS_FACT | C46: Open Tax Lots Fact Id | D46: OPN_TAX_LOTS_FACT_ID | E46: surrogate key of the table | F46: NINI | G46: NUMBER(38,0) | H46: NOT NULL | J46: 1
A47: Open Tax Lots Fact | B47: OPN_TAX_LOTS_FACT | C47: Open Transaction Event Type | D47: OPN_TXN_EV_TP | E47: Source: TAXLOT_DTL_OPN.OPN_TXN_EV_ID RJT Source: TAX_LOT_OPN_MSTR.TAX_LOT_TXN_EV_TP_ID For open lots ? Maxit Event ID For closed lots ? Maxit Event ID of the closing transaction For open and closed lots, this field includes the 'event' of the opening transaction This is a Maxit created Event Name to identify tax lots and create associations between tax lots " | F47: Code | G47: VARCHAR2(40) | H47: NULL | J47: 38
A48: Open Tax Lots Fact | B48: OPN_TAX_LOTS_FACT | C48: Original acquisition date | D48: ORIG_ACQ_DT | E48: Original acquired date is unique and not similar to Acquires date. ORIG_ACQUI_DATE is the acquisition date of the lot, but currently it is only being populated when there is a return of capital payment and it pushes the cost below zero. We currently only display these lots on our tax extract and they are shown on the client’s 1099, however that does not mean we will not display them within other application in the future. | F48: Date | G48: DATE | H48: NULL | J48: 86
A49: Open Tax Lots Fact | B49: OPN_TAX_LOTS_FACT | C49: Original Event Type | D49: ORIG_EV_TP | E49: MAAXIT Source: ORIG_EV_ID Opening transaction original event ID. Used when opening transaction event ID represents a corporate action, in which case the original event ID (such as DRIP BUY, gift, or inheritance, etc. is more important) Maxit ID of the original opening transaction (i.e. would be the id associated with a buy should a reorg/corp action come along and close out that open and create new open with new opening transaction id). Source: ORIG_EV_ID | G49: VARCHAR2(32) | H49: NULL | J49: 40
A50: Open Tax Lots Fact | B50: OPN_TAX_LOTS_FACT | C50: Original Price | D50: ORIG_PRC | E50: Per share price of the opening tax lot. big_prc of the Buy/open short. Will be populated for a sell with opening price. Note: This field cannot be used currently as it is not prorated or adjusted for changes/actions/partial sells where a change in quantity is made. MAXIT Source: TAXLOT_DTL_OPN.ORIG_PRC RJT Source: TAX_LOT_OPN_MSTR.NML_CCY_ORIG_PRC | F50: a | G50: NUMBER(22,6) | H50: NULL | J50: 41
A51: Open Tax Lots Fact | B51: OPN_TAX_LOTS_FACT | C51: Original Proceed | D51: ORIG_PROCD | E51: Net_amount of asgn sell before adding premium. Note: This field cannot be used currently as it is not prorated or adjusted for changes/actions/partial sells where a change in quantity is made. MAXIT Source: TAXLOT_DTL_OPN.ORIG_PROCD RJT Source: TAX_LOT_OPN_MSTR.NML_CCY_ORIG_PROCD_AMT | F51: a | G51: NUMBER(22,6) | H51: NULL | J51: 42
A52: Open Tax Lots Fact | B52: OPN_TAX_LOTS_FACT | C52: Original Transaction Type Code | D52: ORIG_TXN_TP_CD | E52: MAXIT Source: TAXLOT_DTL_OPN.ORIG_TXN_TP RJT Source:TAX_LOT_OPN_MSTR.ORIG_TAX_LOT_TXN_TP_ID Opening transaction original TRAN TYPE ID. Used when opening transaction tran type represents a corporate action, in which case the original tran type (such as DRP, GFT, or INH, etc. is more important) Additional Notes: The purpose of this field is to preserve the TRAN_TYPE with which the position was opened. As opposed to TRAN_TYPE, this field survives corporate actions and wash sale sub-lot allocation. One of the important use cases of ORIGINAL_TRAN_TYPE is alongside of transfers such as ACATs, where the values of INH and GFT indicate gift or inheritance. It should be noted that lots created due to corporate actions on inherited or gifted positions will have ORIGINAL_TRAN_TYPE of INH and GFT, and the TRAN_TYPE set to that of the corporate action. This is a Maxit specific code that describes the category of transaction/action that created the open tax lot. Note: Inherited = INH Inherited than Gifted = ITG - NEW TFS Requirement 195137 Gifted = GFT source: ORIG_TXN_TP existing values: BUY, INH, DRP, ACT, XCH, SED, ATF, RCV, BTO, SHS, EXC, GFT, SCC, STO, CCG, ASN, SPN, RSP, MRG, SDV, RTS, DVR, BPR, WSH, ACQ, OID, MDI, NQSI, LIQ | G52: VARCHAR2(32) | H52: NULL | J52: 43
A53: Open Tax Lots Fact | B53: OPN_TAX_LOTS_FACT | C53: Position Inception Date | D53: POS_INCPTN_DT | E53: Holding date of the opening tax lot. Is available on the sell transaction as well. Note: This should coincide with the acquisition date unless the sale is affected by an action in which the acquisition date changes but the holding date stays the same. i.e. wash sale, gifts, etc.) Used to calculate the term for most cases MAXIT Source: TAXLOT_DTL_OPN.HLDG_DT RJT Source: TAX_LOT_OPN_MSTR.POS_INCPTN_DT | G53: DATE | H53: NULL | J53: 31
A54: Open Tax Lots Fact | B54: OPN_TAX_LOTS_FACT | C54: Position Inception Date Dimension Id | D54: POS_INCPTN_DT_DIM_ID | E54: Synthetic Key identifying a single date in the DATE Dimension | F54: NINI | G54: NUMBER(38,0) | H54: NOT NULL | J54: 85
A55: Open Tax Lots Fact | B55: OPN_TAX_LOTS_FACT | C55: Premium Amount | D55: PREM_AMT | E55: MAXIT Source:TAXLOT_DTL_OPN. PREMIUM RJT Source: None option premium amount added to the underlying stock when an option is assigned to the holder. | F55: a | G55: NUMBER(22,6) | H55: NULL | J55: 44
A56: Open Tax Lots Fact | B56: OPN_TAX_LOTS_FACT | C56: Quantity | D56: QTY | E56: Contains the total shares / PAR value for the open or closed tax lot position. Lot quantity per Maxit When long_short_position = S, always set to (absolute value * -1) When long_short_position = L, always set to absolute value MAXIT Source: TAXLOT_DTL_OPN.QTY RJT Source: TAX_LOT_OPN_ASOF.TAX_LOT_ASOF_QTY | F56: a | G56: NUMBER(22,6) | H56: NULL | J56: 45
A57: Open Tax Lots Fact | B57: OPN_TAX_LOTS_FACT | C57: Reinvestment Lot Flag | D57: RVST_LOT_F | E57: MAXIT Source: TAXLOT_DTL_OPN.RVST_F RJT Source: TAX_LOT_OPN_MSTR.RVST_F For MAXIT it is RJ Derived When original_tran_type = DRP, set to Y ELSE set to N " | G57: VARCHAR2(1) | H57: NULL | J57: 47
A58: Open Tax Lots Fact | B58: OPN_TAX_LOTS_FACT | C58: Session Number | D58: SESN_NUM | F58: NINI | G58: NUMBER(38,0) | H58: NULL | J58: 65
A59: Open Tax Lots Fact | B59: OPN_TAX_LOTS_FACT | C59: Settlement Date | D59: SD | E59: Settlement date of Open/close transaction supplied by RJ or created by Maxit for corporate actions. MAXIT Source: TAXLOT_DTL_OPN.SD RJT Source: TAX_LOT_OPN_MSTR.SD | F59: Date | G59: DATE | H59: NULL | J59: 48
A60: Open Tax Lots Fact | B60: OPN_TAX_LOTS_FACT | C60: Settlement Date Dimension Id | D60: SD_DIM_ID | E60: Synthetic Key identifying a single date in the DATE Dimension | F60: NINI | G60: NUMBER(38,0) | H60: NOT NULL | J60: 84
A61: Open Tax Lots Fact | B61: OPN_TAX_LOTS_FACT | C61: Source Effective Date | D61: SRC_EFF_DT | E61: MAXIT Source: SRC_EFF_DT Transaction date from Maxit. Populated on both open and closed tax lots. corresponds to FABook c_effective_date in the closed tax lot table. | F61: Date | G61: DATE | H61: NULL | J61: 49
A62: Open Tax Lots Fact | B62: OPN_TAX_LOTS_FACT | C62: Source Record Type Code | D62: SRC_RCRD_TP_CD | E62: MAXIT Source: CCAL_TAXLOT_OWNER.TAXLOT_DTL_OPN/CLS.RCRD_TP RJT Source: TAX_LOT_OPN_MSTR SRC_RCRD_TP_ID (CCAL_OWNER.RCRD_TP) values A = Assigned ? Associated with the Closed Tax Lot ONLY B = Buy ? Associated with the Open Tax Lot ONLY C = Cover Short ? Associated with Closed Tax Lot ONLY D = Deliver ? Associated with Closed Tax Lot ONLY E = Expired ? Associated with Closed Tax Lot ONLY H = Transfer of a Short Deliver ? Associated with the Open Tax Lot ONLY L = Short Sell ? Associated with the Open Tax Lot ONLY M = Redemption ? Associated with Closed Tax Lot ONLY R = Receive Record ? Associated with either Open or Closed Tax Lot S = Sell ? Associated with Closed Tax Lot ONLY V = Dividend Reinvestment ? Associated with the Open Tax Lot ONLY Z = record type is not applicable to that type of record | F62: Code | G62: VARCHAR2(40) | H62: NULL | J62: 46
A63: Open Tax Lots Fact | B63: OPN_TAX_LOTS_FACT | C63: Source System Code | D63: SRC_STM_CD | E63: MAXIT: Hardcode ??? We need to setup a source system RJT Source: TAX_LOT_OPN_MSTR.SRC_STM_ID | F63: Code | G63: VARCHAR2(40) | H63: NULL | J63: 2
A64: Open Tax Lots Fact | B64: OPN_TAX_LOTS_FACT | C64: Source System Dimension Id | D64: SRC_STM_DIM_ID | E64: Surrogate Key for Source system dim | F64: NINI | G64: NUMBER(38,0) | H64: NOT NULL | J64: 73
A65: Open Tax Lots Fact | B65: OPN_TAX_LOTS_FACT | C65: Source System Id | D65: SRC_STM_ID | E65: MAXIT: Hardcode ??? We need to setup a source system RJT Source: TAX_LOT_OPN_MSTR.SRC_STM_ID | F65: NINI | G65: NUMBER(38,0) | H65: NULL | J65: 66
A66: Open Tax Lots Fact | B66: OPN_TAX_LOTS_FACT | C66: Source System Name | D66: SRC_STM_NM | E66: Name of the source system e.g., SIS - Securities Industry Software, Raymond James, Raymond James Bank, Shadow Suite MAXIT: Hardcode ??? We need to setup a source system RJT Source: TAX_LOT_OPN_MSTR.SRC_STM_ID | G66: VARCHAR2(60) | H66: NULL | J66: 67
A67: Open Tax Lots Fact | B67: OPN_TAX_LOTS_FACT | C67: system Base Currency Adjusted Cost | D67: SBC_ADJ_COST | E67: Adjusted cost for the Lot MAXIT source: TAXLOT_DTL_OPN.ADJ_COST RJT Source: TAX_LOT_OPN_ASOF NML_CCY_ASOF_ADJ_COST_AMT | F67: a | G67: NUMBER(22,6) | H67: NULL | J67: 59
A68: Open Tax Lots Fact | B68: OPN_TAX_LOTS_FACT | C68: System Base Currency Cost Amount | D68: SBC_COST_AMT | E68: Original total purchase cost of the instrument Buy, the net amount is shown. Sell, cost sold for a sell is displayed. Note: This field cannot be used currently as it is not prorated or adjusted for changes/actions/partial sells where a change in quantity is made. MAXIT Source: TAXLOT_DTL_OPN.ORIG_COST RJT Source:TAX_LOT_OPN_ASOF.NML_ASOF_CRN_COST_AMT | F68: a | G68: NUMBER(22,6) | H68: NULL | J68: 62
A69: Open Tax Lots Fact | B69: OPN_TAX_LOTS_FACT | C69: System Base Currency Disallowed Wash sale Amount | D69: SBC_DISALWD_WASH_SALE_AMT | E69: MAXIT Source: TAXLOT_DTL_OPN.DISALWD_WASHSALE_AMT RJT Source: TAX_LOT_OPN_MSTR.NML_CCY_WASH_SALE_AMT | F69: a | G69: NUMBER(22,6) | H69: NULL | J69: 58
A70: Open Tax Lots Fact | B70: OPN_TAX_LOTS_FACT | C70: System Base Currency Fair Market Value | D70: SBC_FAIR_MKT_VAL | E70: MAXIT Source: TAXLOT_DTL_OPN.FMV For MAXIT (Brokerage) Fair market value of the tax lot at the point of gifting or inheritance Source: FMV For gifted or inherited transactions only. Sourced from: 1) account to account RAD Activity receive record sent to Maxit from RJ 2) CBRS record received from contra firm 3) manual entry by business | F70: a | G70: NUMBER(22,6) | H70: NULL | J70: 60
A71: Open Tax Lots Fact | B71: OPN_TAX_LOTS_FACT | C71: System Base Currency Open Price Factor | D71: SBC_OPN_PRC_FCTR | E71: Price_factor of opening transaction Used for factored bonds MAXIT Source: TAXLOT_DTL_OPN.OPN_FCTR RJT Source: TAX_LOT_OPN_MSTR.NML_CCY_OPN_PRC_FCTR | F71: a | G71: NUMBER(22,6) | H71: NULL | J71: 61
A72: Open Tax Lots Fact | B72: OPN_TAX_LOTS_FACT | C72: System Base Currency Original Price | D72: SBC_ORIG_PRC | E72: Per share price of the opening tax lot. big_prc of the Buy/open short. Will be populated for a sell with opening price. Note: This field cannot be used currently as it is not prorated or adjusted for changes/actions/partial sells where a change in quantity is made. MAXIT Source: TAXLOT_DTL_OPN.ORIG_PRC RJT Source: TAX_LOT_OPN_MSTR.NML_CCY_ORIG_PRC | G72: NUMBER(30,8) | H72: NULL | J72: 63
A73: Open Tax Lots Fact | B73: OPN_TAX_LOTS_FACT | C73: System Base Currency Original Proceed | D73: SBC_ORIG_PROCD | E73: Net_amount of asgn sell before adding premium. Note: This field cannot be used currently as it is not prorated or adjusted for changes/actions/partial sells where a change in quantity is made. MAXIT Source: TAXLOT_DTL_OPN.ORIG_PROCD RJT Source: TAX_LOT_OPN_MSTR.NML_CCY_ORIG_PROCD_AMT | F73: a | G73: NUMBER(22,6) | H73: NULL | J73: 64
A74: Open Tax Lots Fact | B74: OPN_TAX_LOTS_FACT | C74: System Base Currency Unit Cost | D74: SBC_UC | E74: MAXIT Source: TAXLOT_DTL_OPN.UC RJT Source: TAX_LOT_OPN_ASOF.NML_CCY_ASOF_PER_UC_AMT | F74: a | G74: NUMBER(22,6) | H74: NULL | J74: 54
A75: Open Tax Lots Fact | B75: OPN_TAX_LOTS_FACT | C75: Tax Lot External Reference Key Primary | D75: TAX_LOT_EXT_REFR_KEY_PRIM | E75: MAXIT source: MAXIT_IFCE_SEQ_ID RJT Source: TAX_LOT_OPN_MSTR.TAX_LOT_EXT_REFR_KEY_PRIM | F75: Code | G75: VARCHAR2(50) | H75: NOT NULL | J75: 9
A76: Open Tax Lots Fact | B76: OPN_TAX_LOTS_FACT | C76: Tax Lot External Reference Key Quaternary | D76: TAX_LOT_EXT_REFR_KEY_QTRNY | E76: SOurce: TAXLOT_DTL_OPN.REL_LOT_ID RJT Source: TAX_LOT_OPN_MSTR.TAX_LOT_EXT_REFR_KEY_QTRNY | F76: Code | G76: VARCHAR2(40) | H76: NULL | J76: 12
A77: Open Tax Lots Fact | B77: OPN_TAX_LOTS_FACT | C77: Tax Lot External Reference Key Secondary | D77: TAX_LOT_EXT_REFR_KEY_SCDY | E77: source:TAXLOT_DTL_OPN.MAXIT_REL_IFCE_SEQ_ID RJT Source: TAX_LOT_OPN_MSTR.TAX_LOT_EXT_REFR_KEY_SCDY | F77: Code | G77: VARCHAR2(40) | H77: NULL | J77: 10
A78: Open Tax Lots Fact | B78: OPN_TAX_LOTS_FACT | C78: Tax Lot External Reference Key Tertiary | D78: TAX_LOT_EXT_REFR_KEY_TRTY | E78: Source: TAXLOT_DTL_OPN.MAXIT_TXN_LOT_ID RJT Source: TAX_LOT_OPN_MSTR.TAX_LOT_EXT_REFR_KEY_TRTY | F78: Code | G78: VARCHAR2(40) | H78: NULL | J78: 11
A79: Open Tax Lots Fact | B79: OPN_TAX_LOTS_FACT | C79: Tax Lot Type | D79: TAX_LOT_TP | E79: logic: 1. For inherited tax lots, it is set to Inherited 1.1. For Brokerage accounts, this is when the ACAT Type is null and Original Transaction Type is INH from the tax lot detail open table or ACAT Type is INH from the tax lot detail open table 1.2. For RJ Trust accounts, this is when the Tax Lot Transaction Type Identifier is 2846 from the tax lot open master table 2. For gifted or gifted then inherited tax lots, it is set to Gift 2.1 For Brokerage accounts, this is when the ACAT Type is null and Original Transaction Type is GFT from the tax lot detail open table or ACAT Type is GFT or ITG from the tax lot detail open table 2.2 For RJ Trust accounts, this is when the Tax Lot Transaction Type Identifier is 2851 from the tax lot open master table 3. For reinvested tax lots, it is set to Reinvestment 3.1. For Brokerage accounts, this is when the ACAT Type is not GFT, INH or ITG and the Reinvest Flag is Y from the tax lot detail open table 3.2. For RJ Trust accounts, this is when the Tax Lot Transaction Type Identifier is not 2846 or 2851 and the Reinvest Flag is Y from the tax lot open master table 4. For all other tax lots 4.1 For Brokerage accounts, it is the High Level Definition from the record type table where 4.1.1. Open Close Indicator from record type table is O 4.1.2. Realized Closing Flag is N 4.1.3. Opening Transaction Event Id from the tax lot detail open table matches the Transaction Event Id from record type table 4.1.4. Otherwise, if match is not found, then set to null 4.2 For RJ Trust accounts, it is the Classification Value Name from the classification value table where 4.2.1 Tax Lot Transaction Type Identifier from the tax lot open master table matches the Classification Value Identifier from the classification table 4.2.2Classification Source Identifier from the classification table is 84 4.3 Otherwise, if match is not found, then set to null | F79: Name_desc | G79: VARCHAR2(500) | H79: NULL | J79: 74
A80: Open Tax Lots Fact | B80: OPN_TAX_LOTS_FACT | C80: Trade Number | D80: TRD_NUM | E80: MAXIT Source: TAXLOT_DTL_OPN.TRD_NUM | F80: Trade_num | G80: VARCHAR2(80) | H80: NULL | J80: 50
A81: Open Tax Lots Fact | B81: OPN_TAX_LOTS_FACT | C81: transaction initiate date | D81: TXN_INTT_DT | E81: MAXIT Source:TAXLOT_DTL_OPN.TXN_INIT_DT_x000D_ RJT Source: TAX_LOT_OPN_MSTR.TXN_INTT_DT_x000D_ _x000D_ | G81: DATE | H81: NULL | I81: Frozen | J81: 51
A82: Open Tax Lots Fact | B82: OPN_TAX_LOTS_FACT | C82: transaction initiate date dimension id | D82: TXN_INTT_DT_DIM_ID | E82: Synthetic Key identifying a single date in the DATE Dimension | F82: NINI | G82: NUMBER(38,0) | H82: NOT NULL | J82: 83
A83: Open Tax Lots Fact | B83: OPN_TAX_LOTS_FACT | C83: Transaction Type Code | D83: TXN_TP_CD | E83: MAXIT Source: TAXLOT_DTL_OPN.TXN_TP RJT Source: TAX_LOT_OPN_MSTR.ORIG_TAX_LOT_TXN_TP_ID | F83: Code | G83: VARCHAR2(40) | H83: NULL | J83: 52
A84: Open Tax Lots Fact | B84: OPN_TAX_LOTS_FACT | C84: Unit Cost | D84: UC | E84: MAXIT Source: TAXLOT_DTL_OPN.UC RJT Source: TAX_LOT_OPN_ASOF.NML_CCY_ASOF_PER_UC_AMT | F84: a | G84: NUMBER(22,6) | H84: NULL | J84: 53
A85: Open Tax Lots Fact | B85: OPN_TAX_LOTS_FACT | C85: Wash Sale Flag | D85: WASH_SALE_F | E85: MAXIT Source: TAXLOT_DTL_OPN.WASH_SALE_IND RJT Source: TAX_LOT_OPN_MSTR.WASH_SALE_F WASH_SALE_IND on Source. Y= Wash Sale Sublot | F85: Flag | G85: VARCHAR2(1) | H85: NULL | J85: 55
A86: Open Tax Lots Fact | B86: OPN_TAX_LOTS_FACT | C86: Wash Sale Type | D86: WASH_SALE_TP | E86: Wash Sale Type from SRD | F86: Name_desc | G86: VARCHAR2(500) | H86: NULL | J86: 57
A87: Open Tax Lots Fact | B87: OPN_TAX_LOTS_FACT | C87: Zero Cost Basis Flag | D87: ZERO_COST_BSS_F | E87: MAXIT Source TAXLOT_DTL_OPN.ZERO_BSS_IND RJT Source: TAX_LOT_OPN_MSTR.ZERO_BSS_IND_F | F87: Flag | G87: VARCHAR2(1) | H87: NULL | J87: 56

Sheet Table
A1: COLUMN_NAME | B1: DATA_TYPE | C1: NULLABLE | D1: DATA_DEFAULT | E1: COLUMN_ID | F1: COMMENTS
A2: ACAT_TP | B2: VARCHAR2(500 BYTE) | C2: Yes | E2: 17 | F2: MAXIT Source: = TAXLOT_DTL_OPN.ACATTYPE RJT Source: None Type of Transfer indicated by the external source when transferred using ACAT Values GFT = Gift INH = Inherited ITG = Inherited Than Gifted NTT = NonTaxable to Taxable DRIP = A Direct Registration System (DRS)/Direct Reinvestment Plan NULL = none various other values are available as well
A3: ACAT_TP_CD | B3: VARCHAR2(40 BYTE) | C3: Yes | E3: 18 | F3: MAXIT Source: = TAXLOT_DTL_OPN.ACATTYPE RJT Source: None Type of Transfer Code indicated by the external source when transferred using ACAT Values GFT = Gift INH = Inherited ITG = Inherited Than Gifted NTT = NonTaxable to Taxable DRIP = A Direct Registration System (DRS)/Direct Reinvestment Plan NULL = none various other values are available as well
A4: ACG_TP_CD | B4: VARCHAR2(1 BYTE) | C4: Yes | E4: 8 | F4: MAXIT Source: TAXLOT_DTL_OPN.AC_TP RJT Source: TAX_LOT_OPN_MSTR.ACG_TP_CODE Accounting type code from SIS (e.g., 1,2,6). 1= Cash Account 2= Margin Account 3= Special lot 2019 5= Special lot 2013 6= Short margin Account
A5: ACG_TP_DIM_ID | B5: NUMBER(38,0) | C5: No | E5: 15 | F5: MAXIT Source: TAXLOT_DTL_OPN.AC_TP RJT Source: TAX_LOT_OPN_MSTR.ACG_TP_CODE Lookup on Accounting Type Dimension
A6: ACG_TP_ID | B6: NUMBER(38,0) | C6: Yes | E6: 70 | F6: Numeric identifier of the accounting type ID (e.g., 1006, 1001) Lookup using Accounting type Code (MAXIT TAXLOT_DTL_OPN.AC_TP, RJT TAX_LOT_OPN_MSTR.ACG_TP_CODE)
A7: ACG_TP_NM | B7: VARCHAR2(500 BYTE) | C7: Yes | E7: 16 | F7: MAXIT Source: TAXLOT_DTL_OPN.AC_TP RJT Source: TAX_LOT_OPN_MSTR.ACG_TP_CODE Lookup on Accounting Type Dimension Accounting type name (e.g., cash account,margin account)
A8: ACQ_DT | B8: DATE | C8: Yes | E8: 19 | F8: Date on which the lot was acquired MAXIT source: TAXLOT_DTL_OPN.ACQ_DT RJT Source:TAX_LOT_OPN_MSTR.TD
A9: ACQ_DT_DIM_ID | B9: NUMBER(38,0) | C9: No | E9: 75 | F9: Synthetic Key identifying a single date in the DATE Dimension
A10: ADJ_COST | B10: NUMBER(22,6) | C10: Yes | E10: 20 | F10: Adjusted cost for the Lot MAXIT source: TAXLOT_DTL_OPN.ADJ_COST RJT Source: TAX_LOT_OPN_ASOF NML_CCY_ASOF_ADJ_COST_AMT
A11: ADJ_COST_NOT_ACRT_F | B11: VARCHAR2(1 BYTE) | C11: Yes | E11: 36 | F11: MAXIT Source: TAXLOT_DTL_OPN.NULL_F RJT Source: TAX_LOT_OPN_MSTR.NULL_BSS_F Indcates that Adjusted Cost is not accurate due to missing cost on atleast one sublot Source:NULL_F Y = YES – At least one of the associated average cost records is missing average cost N = NO – None of the associated average cost records are missing average cost
A12: AR_DIM_ID | B12: NUMBER(38,0) | C12: No | E12: 7 | F12: Arrangement Id for the account MAXIT Source: TAX_LOT_DTL_OPN/CLS.AR_ID RJT Source:TAX_LOT_OPN_MSTR.AR_ID Lookup on AR_DIM using EFF_DT
A13: AR_ID | B13: NUMBER | C13: Yes | E13: 3 | F13: Arrangement Id for the account MAXIT Source:TAX_LOT_DTL_OPN/CLS.AR_ID RJT Source:TAX_LOT_OPN_MSTR.AR_ID
... A21: COST_BSS_SHRHLR_PVDD_CD | B21: VARCHAR2(1 BYTE) | C21: Yes | E21: 21 | F21: Cost Basis provided by the client. Y=Yes, N= No other code values 0 (zero) and Null. We do not have documentation on these codes MAXIT Source:TAXLOT_DTL_OPN.BSS_SHP RJT Source: None
A22: CRT_DTM | B22: TIMESTAMP(6) | C22: No | D22: SYSDATE | E22: 65
A23: CRT_USR_NM | B23: VARCHAR2(256 BYTE) | C23: No | D23: USER | E23: 66 | F23: The name that represents the user who created an occurrence of a/an Position Open Tax Lots Fact.
A24: CTF_NUM | B24: VARCHAR2(40 BYTE) | C24: Yes | E24: 24 | F24: MAXIT Source:TAXLOT_DTL_OPN.CTF_NUM RJT Source: TAX_LOT_OPN_MSTR.TAX_LOT_CTF_NUM
A25: CTF_NUM_PFX | B25: VARCHAR2(40 BYTE) | C25: Yes | E25: 25 | F25: MAXIT Source:TAXLOT_DTL_OPN.CTF_NUM_PFX RJT Source: TAX_LOT_OPN_MSTR.TAX_LOT_CTF_NUM_PFX
A26: DISALWD_WASH_SALE_AMT | B26: NUMBER(22,6) | C26: Yes | E26: 27 | F26: MAXIT Source: TAXLOT_DTL_OPN.DISALWD_WASHSALE_AMT RJT Source: TAX_LOT_OPN_MSTR.NML_CCY_WASH_SALE_AMT
A27: DUAL_BSS_F | B27: VARCHAR2(1 BYTE) | C27: Yes | E27: 83 | F27: Possible values Y = Record is a depreciated dual basis gift N = Record is not a depreciated dual basis gift For Brokerage accounts If the ACAT type is null and the Original Transaction Type is GFT from tax lot detail open And Fair market value from tax lot detail open is greater than zero And Adjusted cost amount from tax lot detail open is greater than zero And Fair market value is less than or equal to adjusted cost amount then Set to Y or If the ACAT Type is GFT or ITG from tax lot detail open and Fair market value from tax lot detail open is greater than zero And Adjusted cost amount from tax lot detail open is greater than zero And Fair market value is less than or equal to adjusted cost amount then Set to Y Otherwise, set to N For RJ Trust accounts If the Tax Lot Transaction Type Identifier is 2851 from the tax lot open master table and the SBC As Of Fair Market Value from the tax lot open as of table is greater than zero and the SBC As Of Adjusted Cost Amount from the tax lot open as of table is greater than zero and the SBC As Of Fair Market Value is less than or equal to the SBC As Of Adjusted Cost Amount then Set to Y Otherwise, set to N
A28: EFF_DT | B28: DATE | C28: Yes | E28: 14 | F28: MAXIT Source: TAXLOT_DTL_OPN.EFF_DT RJT Source: TAX_LOT_OPN_ASOF.EFF_FM_DT
A29: EFF_DT_DIM_ID | B29: NUMBER(38,0) | C29: No | E29: 73 | F29: Synthetic Key identifying a single date in the DATE Dimension
A30: END_DT | B30: DATE | C30: No | E30: 13 | F30: MAXIT Source: TAXLOT_DTL_OPN.END_DT RJT Source: TAX_LOT_OPN_ASOF.EFF_TO_DT
A31: END_DT_DIM_ID | B31: NUMBER(38,0) | C31: No | E31: 74 | F31: Synthetic Key identifying a single date in the DATE Dimension
A32: EXG_RATE | B32: NUMBER(22,6) | C32: Yes | E32: 28 | F32: MAXIT Source: TAXLOT_DTL_OPN.EXG_RATE RJT Source: TAX_LOT_OPN_ASOF.SBC_EXG_RATE
A33: FAIR_MKT_VAL_OF_GIFT_OR_INHTN | B33: NUMBER(22,6) | C33: Yes | E33: 29 | F33: MAXIT Source: TAXLOT_DTL_OPN.FMV RJT SOurce: TAX_LOT_OPN_ASOF.NML_CCY_ASOF_FAIR_MKT_VAL_AMT For MAXIT (Brokerage) Fair market value of the tax lot at the point of gifting or inheritance Source: FMV For gifted or inherited transactions only. Sourced from: 1) account to account RAD Activity receive record sent to Maxit from RJ 2) CBRS record received from contra firm 3) manual entry by business
A34: GIFT_DT | B34: DATE | C34: Yes | E34: 30 | F34: MAXIT Source: TAXLOT_DTL_OPN.GIFT_DT RJT Source: TAX_LOT_OPN_MSTR.GIFT_DT For gifted tax lots this gives date of gift. Source: GIFT_DT
A35: GIFT_DT_DIM_ID | B35: NUMBER(38,0) | C35: No | E35: 76 | F35: Synthetic Key identifying a single date in the DATE Dimension
A36: IMT_PD_DIM_ID | B36: NUMBER(38,0) | C36: No | E36: 6 | F36: Surrogate key for Instrument Product Dim
A37: LAST_UDT_DTM | B37: TIMESTAMP(6) | C37: No | D37: SYSDATE | E37: 71
A38: LAST_UDT_USR_NM | B38: VARCHAR2(256 BYTE) | C38: No | D38: USER | E38: 72 | F38: The name that represents the user or application who inserted, updated, or deleted each occurrence of Position Open Tax Lots Fact.
A39: LIFE_TO_DTD_MKT_DCN | B39: NUMBER(22,6) | C39: Yes | E39: 34 | F39: Life to date market discount amount Total market discount accrued since the purchase of the bond MAXIT Source: TAXLOT_DTL_OPN.LTD_MKT_DISCOUNT
A40: LONG_SHRT_POS_CD | B40: VARCHAR2(1 BYTE) | C40: Yes | E40: 32 | F40: A value that represents the tax lot being a long or short position. Valid Values: L = Long S = Short MAXIT Source: TAXLOT_DTL_OPN.LONG_SHRT_POS rjt sOURCE: TAX_LOT_OPN_MSTR.POS_LONG_SHRT_CODE
A41: LOSS_NOT_ALWD_F | B41: VARCHAR2(1 BYTE) | C41: Yes | E41: 33 | F41: MAXIT Source: TAXLOT_DTL_OPN.LOSS_NOT_ALLOWED RJT Source: None In a cash and stock merger the client may not be allowed to take a loss on the disposition of the old stock, any losses are rolled into the new stock. Merger / Acquisition or Corporate Inversion Transactions. This field is currently used on Closed Tax Lot Tax Reporting at this time. Values: N = No, Loss allowed Y = Yes, No Loss allowed
A42: MISS_COST_BSS_F | B42: VARCHAR2(1 BYTE) | C42: Yes | E42: 35 | F42: Indicates that Cost basis is not available for this position MAXIT Source: TAXLOT_DTL_OPN.MISS_COST_F RJT Source: TAX_LOT_OPN_MSTR.MISS_COST_F
A43: MISS_IVS_COST_F | B43: VARCHAR2(1 BYTE) | C43: Yes | E43: 84 | F43: For Brokerage accounts If the reinvest flag from tax lot detail open is not equal to Y If the missing cost flag from tax lot detail open is Y, then set to Y If the missing average cost flag (null flag) from tax lot detail open is Y, then set to Y Otherwise, set to N For RJ Trust accounts If the reinvest flag from tax lot open master is not equal to Y If the Missing Cost Flag from the tax lot open master table is Y, then set to Y If the Null Basis Flag from the tax lot open master table is Y, then set to Y Otherwise, set to N
A44: OPN_PRC_FCTR | B44: NUMBER(22,6) | C44: Yes | E44: 37 | F44: Price_factor of opening transaction Used for factored bonds MAXIT Source: TAXLOT_DTL_OPN.OPN_FCTR RJT Source: TAX_LOT_OPN_MSTR.NML_CCY_OPN_PRC_FCTR
A45: OPN_TAX_LOTS_FACT_ID | B45: NUMBER(38,0) | C45: No | E45: 1
A46: OPN_TXN_EV_TP | B46: VARCHAR2(40 BYTE) | C46: Yes | E46: 38 | F46: Source: TAXLOT_DTL_OPN.OPN_TXN_EV_ID RJT Source: TAX_LOT_OPN_MSTR.TAX_LOT_TXN_EV_TP_ID For open lots – Maxit Event ID For closed lots – Maxit Event ID of the closing transaction For open and closed lots, this field includes the 'event' of the opening transaction This is a Maxit created Event Name to identify tax lots and create associations between tax lots"
A47: ORIG_EV_TP | B47: VARCHAR2(32 BYTE) | C47: Yes | E47: 40 | F47: MAAXIT Source: ORIG_EV_ID Opening transaction original event ID. Used when opening transaction event ID represents a corporate action, in which case the original event ID (such as DRIP BUY, gift, or inheritance, etc. is more important) Maxit ID of the original opening transaction (i.e. would be the id associated with a buy should a reorg/corp action come along and close out that open and create new open with new opening transaction id). Source: ORIG_EV_ID
A48: ORIG_PRC | B48: NUMBER(22,6) | C48: Yes | E48: 41 | F48: Per share price of the opening tax lot.big_prc of the Buy/open short. Will be populated for a sell with opening price. Note: This field cannot be used currently as it is not prorated or adjusted for changes/actions/partial sells where a change in quantity is made. MAXIT Source: TAXLOT_DTL_OPN.ORIG_PRC RJT Source: TAX_LOT_OPN_MSTR.NML_CCY_ORIG_PRC
A49: ORIG_PROCD | B49: NUMBER(22,6) | C49: Yes | E49: 42 | F49: Net_amount of asgn sell before adding premium. Note: This field cannot be used currently as it is not prorated or adjusted for changes/actions/partial sells where a change in quantity is made. MAXIT Source: TAXLOT_DTL_OPN.ORIG_PROCD RJT Source: TAX_LOT_OPN_MSTR.NML_CCY_ORIG_PROCD_AMT
A50: ORIG_TXN_TP_CD | B50: VARCHAR2(32 BYTE) | C50: Yes | E50: 43 | F50: MAXIT Source: TAXLOT_DTL_OPN.ORIG_TXN_TP RJT Source:TAX_LOT_OPN_MSTR.ORIG_TAX_LOT_TXN_TP_ID Opening transaction original TRAN TYPE ID. Used when opening transaction tran type represents a corporate action, in which case the original tran type (such as DRP, GFT, or INH, etc. is more important) Additional Notes: The purpose of this field is to preserve the TRAN_TYPE with which the position was opened. As opposed to TRAN_TYPE, this field survives corporate actions and wash sale sub-lot allocation. One of the important use cases of ORIGINAL_TRAN_TYPE is alongside of transfers such as ACATs, where the values of INH and GFT indicate gift or inheritance. It should be noted that lots created due to corporate actions on inherited or gifted positions will have ORIGINAL_TRAN_TYPE of INH and GFT, and the TRAN_TYPE set to that of the corporate action. This is a Maxit specific code that describes the category of transaction/action that created the open tax lot. Note: Inherited = INH Inherited than Gifted = ITG - NEW TFS Requirement 195137 Gifted = GFT source: ORIG_TXN_TP existing values: BUY, INH, DRP, ACT, XCH, SED, ATF, RCV, BTO, SHS, EXC, GFT, SCC, STO, CCG, ASN, SPN, RSP, MRG, SDV, RTS, DVR, BPR, WSH, ACQ, OID, MDI, NQSI, LIQ
A51: POS_INCPTN_DT | B51: DATE | C51: Yes | E51: 31 | F51: Holding date of the opening tax lot. Is available on the sell transaction as well. Note: This should coincide with the acquisition date unless the sale is affected by an action in which the acquisition date changes but the holding date stays the same. i.e. wash sale, gifts, etc.) Used to calculate the term for most cases MAXIT Source: TAXLOT_DTL_OPN.HLDG_DT RJT Source: TAX_LOT_OPN_MSTR.POS_INCPTN_DT
A52: POS_INCPTN_DT_DIM_ID | B52: NUMBER(38,0) | C52: No | E52: 79 | F52: Synthetic Key identifying a single date in the DATE Dimension
A53: PREM_AMT | B53: NUMBER(22,6) | C53: Yes | E53: 44 | F53: MAXIT Source:TAXLOT_DTL_OPN. PREMIUM RJT Source: None option premium amount added to the underlying stock when an option is assigned to the holder.
A54: QTY | B54: NUMBER(22,6) | C54: Yes | E54: 45 | F54: Contains the total shares / PAR value for the open or closed tax lot position. Lot quantity per Maxit When long_short_position = S, always set to (absolute value * -1) When long_short_position = L, always set to absolute value MAXIT Source: TAXLOT_DTL_OPN.QTY RJT Source: TAX_LOT_OPN_ASOF.TAX_LOT_ASOF_QTY
A55: RVST_LOT_F | B55: VARCHAR2(1 BYTE) | C55: Yes | E55: 47 | F55: MAXIT Source: TAXLOT_DTL_OPN.RVST_F RJT Source: TAX_LOT_OPN_MSTR.RVST_F For MAXIT it is RJ Derived When original_tran_type = DRP, set to Y ELSE set to N "
A56: SBC_ADJ_COST | B56: NUMBER(22,6) | C56: Yes | E56: 59 | F56: Adjusted cost for the Lot MAXIT source: TAXLOT_DTL_OPN.ADJ_COST RJT Source: TAX_LOT_OPN_ASOF NML_CCY_ASOF_ADJ_COST_AMT
A57: SBC_COST_AMT | B57: NUMBER(22,6) | C57: Yes | E57: 62 | F57: Original total purchase cost of the instrument Buy, the net amount is shown. Sell, cost sold for a sell is displayed. Note: This field cannot be used currently as it is not prorated or adjusted for changes/actions/partial sells where a change in quantity is made. MAXIT Source: TAXLOT_DTL_OPN.ORIG_COST RJT Source:TAX_LOT_OPN_ASOF.NML_ASOF_CRN_COST_AMT
... A65: SD_DIM_ID | B65: NUMBER(38,0) | C65: No | E65: 77 | F65: Synthetic Key identifying a single date in the DATE Dimension
A66: SESN_NUM | B66: NUMBER(38,0) | C66: Yes | E66: 67
A67: SRC_EFF_DT | B67: DATE | C67: Yes | E67: 49 | F67: MAXIT Source: SRC_EFF_DT Transaction date from Maxit. Populated on both open and closed tax lots. corresponds to FABook c_effective_date in the closed tax lot table.
A68: SRC_RCRD_TP_CD | B68: VARCHAR2(40 BYTE) | C68: Yes | E68: 46 | F68: MAXIT Source: TAXLOT_OWNER.TAXLOT_DTL_OPN/CLS.RCRD_TP RJT Source: TAX_LOT_OPN_MSTR SRC_RCRD_TP_ID (CCAL_OWNER.RCRD_TP) values A = Assigned – Associated with the Closed Tax Lot ONLY B = Buy – Associated with the Open Tax Lot ONLY C = Cover Short – Associated with Closed Tax Lot ONLY D = Deliver – Associated with Closed Tax Lot ONLY E = Expired – Associated with Closed Tax Lot ONLY H = Transfer of a Short Deliver – Associated with the Open Tax Lot ONLY L = Short Sell – Associated with the Open Tax Lot ONLY M = Redemption – Associated with Closed Tax Lot ONLY R = Receive Record – Associated with either Open or Closed Tax Lot S = Sell – Associated with Closed Tax Lot ONLY V = Dividend Reinvestment – Associated with the Open Tax Lot ONLY Z = record type is not applicable to that type of record
A69: SRC_STM_CD | B69: VARCHAR2(40 BYTE) | C69: Yes | E69: 2 | F69: MAXIT: Hardcode ??? We need to setup a source system RJT Source: TAX_LOT_OPN_MSTR.SRC_STM_ID
A70: SRC_STM_DIM_ID | B70: NUMBER(38,0) | C70: No | E70: 80 | F70: Surrogate Key for Source system dim
A71: SRC_STM_ID | B71: NUMBER(38,0) | C71: Yes | E71: 68 | F71: MAXIT: Hardcode ??? We need to setup a source system RJT Source: TAX_LOT_OPN_MSTR.SRC_STM_ID
A72: SRC_STM_NM | B72: VARCHAR2(60 BYTE) | C72: Yes | E72: 69 | F72: Name of the source system e.g., SIS - Securities Industry Software, Raymond James, Raymond James Bank, Shadow Suite MAXIT: Hardcode ??? We need to setup a source system RJT Source: TAX_LOT_OPN_MSTR.SRC_STM_ID
A73: TAX_LOT_EXT_REFR_KEY_PRIM | B73: VARCHAR2(50 BYTE) | C73: Yes | E73: 9 | F73: MAXIT source: MAXIT_IFCE_SEQ_ID RJT Source: TAX_LOT_OPN_MSTR.TAX_LOT_EXT_REFR_KEY_PRIM
A74: TAX_LOT_EXT_REFR_KEY_QTRNY | B74: NUMBER(38,0) | C74: Yes | E74: 12 | F74: SOurce: TAXLOT_DTL_OPN.REL_LOT_ID RJT Source: TAX_LOT_OPN_MSTR.TAX_LOT_EXT_REFR_KEY_QTRNY
A75: TAX_LOT_EXT_REFR_KEY_SCDY | B75: VARCHAR2(40 BYTE) | C75: Yes | E75: 10 | F75: source:TAXLOT_DTL_OPN.MAXIT_REL_IFCE_SEQ_ID RJT Source: TAX_LOT_OPN_MSTR.TAX_LOT_EXT_REFR_KEY_SCDY
A76: TAX_LOT_EXT_REFR_KEY_TRTY | B76: NUMBER(38,0) | C76: Yes | E76: 11 | F76: Source: TAXLOT_DTL_OPN.MAXIT_TXN_LOT_ID RJT Source: TAX_LOT_OPN_MSTR.TAX_LOT_EXT_REFR_KEY_TRTY
A77: TAX_LOT_TP | B77: VARCHAR2(500 BYTE) | C77: Yes | E77: 81 | F77: logic: 1. For inherited tax lots, it is set to Inherited 1.1. For Brokerage accounts, this is when the ACAT Type is null and Original Transaction Type is INH from the tax lot detail open table or ACAT Type is INH from the tax lot detail open table 1.2. For RJ Trust accounts, this is when the Tax Lot Transaction Type Identifier is 2846 from the tax lot open master table 2. For gifted or gifted then inherited tax lots, it is set to Gift 2.1 For Brokerage accounts, this is when the ACAT Type is null and Original Transaction Type is GFT from the tax lot detail open table or ACAT Type is GFT or ITG from the tax lot detail open table 2.2 For RJ Trust accounts, this is when the Tax Lot Transaction Type Identifier is 2851 from the tax lot open master table 3. For reinvested tax lots, it is set to Reinvestment 3.1. For Brokerage accounts, this is when the ACAT Type is not GFT, INH or ITG and the Reinvest Flag is Y from the tax lot detail open table 3.2. For RJ Trust accounts, this is when the Tax Lot Transaction Type Identifier is not 2846 or 2851 and the Reinvest Flag is Y from the tax lot open master table 4. For all other tax lots 4.1 For Brokerage accounts, it is the High Level Definition from the record type table where 4.1.1. Open Close Indicator from record type table is O 4.1.2. Realized Closing Flag is N 4.1.3. Opening Transaction Event Id from the tax lot detail open table matches the Transaction Event Id from record type table 4.1.4. Otherwise, if match is not found, then set to null 4.2 For RJ Trust accounts, it is the Classification Value Name from the classification value table where 4.2.1 Tax Lot Transaction Type Identifier from the tax lot open master table matches the Classification Value Identifier from the classification table 4.2.2Classification Source Identifier from the classification table is 84 4.3 Otherwise, if match is not found, then set to null
A78: TRD_NUM | B78: VARCHAR2(80 BYTE) | C78: Yes | E78: 50 | F78: MAXIT Source: TAXLOT_DTL_OPN.TRD_NUM
... A85: ZERO_COST_BSS_F | B85: VARCHAR2(2 BYTE) | C85: Yes | E85: 56 | F85: MAXIT Source TAXLOT_DTL_OPN.ZERO_BSS_IND RJT Source: TAX_LOT_OPN_MSTR.ZERO_BSS_IND_F
